{
"meta":{"test_sets":[],"test_metrics":[],"learn_metrics":[{"best_value":"Min","name":"RMSE"}],"launch_mode":"Train","parameters":"","iteration_count":1000,"learn_sets":["learn"],"name":"experiment"},
"iterations":[
{"learn":[14.59871775],"iteration":0,"passed_time":0.1418694678,"remaining_time":141.7275983},
{"learn":[14.22518863],"iteration":1,"passed_time":0.1446535363,"remaining_time":72.18211463},
{"learn":[13.8866124],"iteration":2,"passed_time":0.1464429121,"remaining_time":48.66786112},
{"learn":[13.52356875],"iteration":3,"passed_time":0.1479024609,"remaining_time":36.82771278},
{"learn":[13.18870211],"iteration":4,"passed_time":0.1496744837,"remaining_time":29.78522225},
{"learn":[12.9124226],"iteration":5,"passed_time":0.1511659008,"remaining_time":25.0431509},
{"learn":[12.60003351],"iteration":6,"passed_time":0.1525965151,"remaining_time":21.64690565},
{"learn":[12.32990573],"iteration":7,"passed_time":0.1537243167,"remaining_time":19.06181527},
{"learn":[12.0660619],"iteration":8,"passed_time":0.1547208531,"remaining_time":17.03648505},
{"learn":[11.77309809],"iteration":9,"passed_time":0.1555159112,"remaining_time":15.39607521},
{"learn":[11.49227636],"iteration":10,"passed_time":0.1564286409,"remaining_time":14.0643569},
{"learn":[11.26264833],"iteration":11,"passed_time":0.1577176684,"remaining_time":12.98542136},
{"learn":[11.04260393],"iteration":12,"passed_time":0.158966806,"remaining_time":12.06924904},
{"learn":[10.79916926],"iteration":13,"passed_time":0.1599317145,"remaining_time":11.26376218},
{"learn":[10.5541002],"iteration":14,"passed_time":0.1606245319,"remaining_time":10.5476776},
{"learn":[10.31918115],"iteration":15,"passed_time":0.1618614154,"remaining_time":9.954477048},
{"learn":[10.10004441],"iteration":16,"passed_time":0.1625351086,"remaining_time":9.398353633},
{"learn":[9.894556723],"iteration":17,"passed_time":0.1631566443,"remaining_time":8.901101372},
{"learn":[9.690174082],"iteration":18,"passed_time":0.1638885313,"remaining_time":8.46182364},
{"learn":[9.506034866],"iteration":19,"passed_time":0.1646329835,"remaining_time":8.067016191},
{"learn":[9.338524633],"iteration":20,"passed_time":0.1652710976,"remaining_time":7.704781169},
{"learn":[9.170203312],"iteration":21,"passed_time":0.1660962915,"remaining_time":7.383735142},
{"learn":[9.010299969],"iteration":22,"passed_time":0.1669806143,"remaining_time":7.093046093},
{"learn":[8.843866678],"iteration":23,"passed_time":0.1677753952,"remaining_time":6.822866071},
{"learn":[8.690548059],"iteration":24,"passed_time":0.1684538861,"remaining_time":6.569701559},
{"learn":[8.555307687],"iteration":25,"passed_time":0.1696913939,"remaining_time":6.35690068},
{"learn":[8.413851302],"iteration":26,"passed_time":0.1702866337,"remaining_time":6.136625726},
{"learn":[8.29256019],"iteration":27,"passed_time":0.1716498726,"remaining_time":5.958702721},
{"learn":[8.162193833],"iteration":28,"passed_time":0.1723931871,"remaining_time":5.772199472},
{"learn":[8.040736294],"iteration":29,"passed_time":0.1731624524,"remaining_time":5.598919294},
{"learn":[7.921220278],"iteration":30,"passed_time":0.1738324652,"remaining_time":5.433666411},
{"learn":[7.809589039],"iteration":31,"passed_time":0.1745138467,"remaining_time":5.279043862},
{"learn":[7.699675801],"iteration":32,"passed_time":0.1752251297,"remaining_time":5.134627286},
{"learn":[7.60645267],"iteration":33,"passed_time":0.1759436292,"remaining_time":4.998868994},
{"learn":[7.498880302],"iteration":34,"passed_time":0.1766218986,"remaining_time":4.869718061},
{"learn":[7.401158744],"iteration":35,"passed_time":0.1773131371,"remaining_time":4.748051784},
{"learn":[7.306431077],"iteration":36,"passed_time":0.1779749713,"remaining_time":4.632159388},
{"learn":[7.223863468],"iteration":37,"passed_time":0.178873339,"remaining_time":4.528319792},
{"learn":[7.143477682],"iteration":38,"passed_time":0.1795070016,"remaining_time":4.42323663},
{"learn":[7.062817131],"iteration":39,"passed_time":0.1802374557,"remaining_time":4.325698937},
{"learn":[6.990793435],"iteration":40,"passed_time":0.1813629374,"remaining_time":4.24212334},
{"learn":[6.931862224],"iteration":41,"passed_time":0.1821128872,"remaining_time":4.153908237},
{"learn":[6.858296558],"iteration":42,"passed_time":0.1831527206,"remaining_time":4.076212876},
{"learn":[6.786268161],"iteration":43,"passed_time":0.1843636974,"remaining_time":4.005720334},
{"learn":[6.717118549],"iteration":44,"passed_time":0.1854516748,"remaining_time":3.935696653},
{"learn":[6.652948106],"iteration":45,"passed_time":0.1862366778,"remaining_time":3.862386753},
{"learn":[6.589686076],"iteration":46,"passed_time":0.1874356244,"remaining_time":3.800556383},
{"learn":[6.531283097],"iteration":47,"passed_time":0.1880617862,"remaining_time":3.729892094},
{"learn":[6.471368031],"iteration":48,"passed_time":0.1887191857,"remaining_time":3.662692768},
{"learn":[6.416481395],"iteration":49,"passed_time":0.1893614673,"remaining_time":3.597867879},
{"learn":[6.369870822],"iteration":50,"passed_time":0.1900650944,"remaining_time":3.536701463},
{"learn":[6.325678067],"iteration":51,"passed_time":0.1907384325,"remaining_time":3.477308346},
{"learn":[6.275766122],"iteration":52,"passed_time":0.1914863572,"remaining_time":3.421463778},
{"learn":[6.224773967],"iteration":53,"passed_time":0.192169885,"remaining_time":3.36653169},
{"learn":[6.182249254],"iteration":54,"passed_time":0.1929021391,"remaining_time":3.314409481},
{"learn":[6.139904173],"iteration":55,"passed_time":0.1935166647,"remaining_time":3.262138062},
{"learn":[6.100525536],"iteration":56,"passed_time":0.1941909882,"remaining_time":3.212668453},
{"learn":[6.062568564],"iteration":57,"passed_time":0.1948729496,"remaining_time":3.165005491},
{"learn":[6.030559288],"iteration":58,"passed_time":0.1955568785,"remaining_time":3.118966486},
{"learn":[5.997931376],"iteration":59,"passed_time":0.1963684398,"remaining_time":3.07643889},
{"learn":[5.964103835],"iteration":60,"passed_time":0.1972154346,"remaining_time":3.035824477},
{"learn":[5.933729724],"iteration":61,"passed_time":0.1981745432,"remaining_time":2.998189056},
{"learn":[5.901932711],"iteration":62,"passed_time":0.198956037,"remaining_time":2.959076296},
{"learn":[5.873727795],"iteration":63,"passed_time":0.1998485767,"remaining_time":2.922785434},
{"learn":[5.846485734],"iteration":64,"passed_time":0.2007799812,"remaining_time":2.888142807},
{"learn":[5.820630862],"iteration":65,"passed_time":0.2017781393,"remaining_time":2.855466395},
{"learn":[5.793646238],"iteration":66,"passed_time":0.2030633971,"remaining_time":2.827733575},
{"learn":[5.765388646],"iteration":67,"passed_time":0.2038599189,"remaining_time":2.794080065},
{"learn":[5.747073912],"iteration":68,"passed_time":0.2048362681,"remaining_time":2.763805298},
{"learn":[5.722315217],"iteration":69,"passed_time":0.2060637744,"remaining_time":2.737704431},
{"learn":[5.699970599],"iteration":70,"passed_time":0.206783592,"remaining_time":2.705661366},
{"learn":[5.682732647],"iteration":71,"passed_time":0.2074876278,"remaining_time":2.67428498},
{"learn":[5.663525791],"iteration":72,"passed_time":0.2082290891,"remaining_time":2.644224186},
{"learn":[5.642381613],"iteration":73,"passed_time":0.2088824631,"remaining_time":2.613853524},
{"learn":[5.621404779],"iteration":74,"passed_time":0.2095506486,"remaining_time":2.584458},
{"learn":[5.602460129],"iteration":75,"passed_time":0.2102467354,"remaining_time":2.556157677},
{"learn":[5.587337574],"iteration":76,"passed_time":0.2110526071,"remaining_time":2.529890342},
{"learn":[5.572393026],"iteration":77,"passed_time":0.2117180637,"remaining_time":2.502616086},
{"learn":[5.558425806],"iteration":78,"passed_time":0.2125090138,"remaining_time":2.477478503},
{"learn":[5.541518902],"iteration":79,"passed_time":0.2132486163,"remaining_time":2.452359088},
{"learn":[5.526157283],"iteration":80,"passed_time":0.2140771631,"remaining_time":2.428850777},
{"learn":[5.511746977],"iteration":81,"passed_time":0.2151764341,"remaining_time":2.408926421},
{"learn":[5.504975022],"iteration":82,"passed_time":0.2154964159,"remaining_time":2.380845945},
{"learn":[5.493980522],"iteration":83,"passed_time":0.2163947904,"remaining_time":2.359733667},
{"learn":[5.480745463],"iteration":84,"passed_time":0.2174461605,"remaining_time":2.340743963},
{"learn":[5.464052013],"iteration":85,"passed_time":0.2181498068,"remaining_time":2.318475854},
{"learn":[5.449143727],"iteration":86,"passed_time":0.2188644583,"remaining_time":2.296818971},
{"learn":[5.438255432],"iteration":87,"passed_time":0.2195500029,"remaining_time":2.275336394},
{"learn":[5.425927931],"iteration":88,"passed_time":0.220238203,"remaining_time":2.254348347},
{"learn":[5.412331217],"iteration":89,"passed_time":0.2209075607,"remaining_time":2.233620891},
{"learn":[5.400691499],"iteration":90,"passed_time":0.2217526807,"remaining_time":2.215089965},
{"learn":[5.391618744],"iteration":91,"passed_time":0.2224114403,"remaining_time":2.195104215},
{"learn":[5.380766572],"iteration":92,"passed_time":0.2231511568,"remaining_time":2.176323648},
{"learn":[5.372207183],"iteration":93,"passed_time":0.2237558209,"remaining_time":2.156625253},
{"learn":[5.362918837],"iteration":94,"passed_time":0.2244507419,"remaining_time":2.138188647},
{"learn":[5.348292324],"iteration":95,"passed_time":0.2251496109,"remaining_time":2.120158836},
{"learn":[5.339772295],"iteration":96,"passed_time":0.226193419,"remaining_time":2.105697499},
{"learn":[5.331515983],"iteration":97,"passed_time":0.2270426677,"remaining_time":2.089719248},
{"learn":[5.323861644],"iteration":98,"passed_time":0.2280636473,"remaining_time":2.075609557},
{"learn":[5.313277281],"iteration":99,"passed_time":0.2288643097,"remaining_time":2.059778787},
{"learn":[5.30685627],"iteration":100,"passed_time":0.2297764652,"remaining_time":2.045238042},
{"learn":[5.29652059],"iteration":101,"passed_time":0.2306448026,"remaining_time":2.030578752},
{"learn":[5.288350766],"iteration":102,"passed_time":0.2313750299,"remaining_time":2.014984484},
{"learn":[5.27993346],"iteration":103,"passed_time":0.232073217,"remaining_time":1.999400023},
{"learn":[5.271789139],"iteration":104,"passed_time":0.2327111671,"remaining_time":1.983585663},
{"learn":[5.262684686],"iteration":105,"passed_time":0.2334657256,"remaining_time":1.96904112},
{"learn":[5.251619772],"iteration":106,"passed_time":0.2341407277,"remaining_time":1.954090372},
{"learn":[5.241012171],"iteration":107,"passed_time":0.234805612,"remaining_time":1.939320425},
{"learn":[5.232684032],"iteration":108,"passed_time":0.2355132298,"remaining_time":1.925158603},
{"learn":[5.224267141],"iteration":109,"passed_time":0.2364678073,"remaining_time":1.913239532},
{"learn":[5.216324968],"iteration":110,"passed_time":0.2371615105,"remaining_time":1.899428674},
{"learn":[5.211102527],"iteration":111,"passed_time":0.2378979249,"remaining_time":1.88619069},
{"learn":[5.206364257],"iteration":112,"passed_time":0.2385392139,"remaining_time":1.872427281},
{"learn":[5.196937641],"iteration":113,"passed_time":0.2392188406,"remaining_time":1.859192042},
{"learn":[5.190746047],"iteration":114,"passed_time":0.2399134457,"remaining_time":1.84629043},
{"learn":[5.181885213],"iteration":115,"passed_time":0.2407490518,"remaining_time":1.834673808},
{"learn":[5.178293568],"iteration":116,"passed_time":0.2412736896,"remaining_time":1.820894598},
{"learn":[5.170991438],"iteration":117,"passed_time":0.2422111545,"remaining_time":1.810425748},
{"learn":[5.166257212],"iteration":118,"passed_time":0.242945736,"remaining_time":1.798615071},
{"learn":[5.161421246],"iteration":119,"passed_time":0.2436982393,"remaining_time":1.787120422},
{"learn":[5.158223542],"iteration":120,"passed_time":0.244579302,"remaining_time":1.776737243},
{"learn":[5.15470988],"iteration":121,"passed_time":0.2451438812,"remaining_time":1.764232194},
{"learn":[5.146388143],"iteration":122,"passed_time":0.2458899031,"remaining_time":1.753215},
{"learn":[5.139529364],"iteration":123,"passed_time":0.2466782862,"remaining_time":1.742662732},
{"learn":[5.134276023],"iteration":124,"passed_time":0.2478928334,"remaining_time":1.735249834},
{"learn":[5.128536065],"iteration":125,"passed_time":0.2490306212,"remaining_time":1.72740288},
{"learn":[5.123300353],"iteration":126,"passed_time":0.2497136067,"remaining_time":1.716535265},
{"learn":[5.116200518],"iteration":127,"passed_time":0.2509243195,"remaining_time":1.709421927},
{"learn":[5.108728704],"iteration":128,"passed_time":0.251723292,"remaining_time":1.699620057},
{"learn":[5.104075866],"iteration":129,"passed_time":0.2523816757,"remaining_time":1.689015829},
{"learn":[5.100317606],"iteration":130,"passed_time":0.2530633047,"remaining_time":1.678717647},
{"learn":[5.095814182],"iteration":131,"passed_time":0.253703352,"remaining_time":1.668291739},
{"learn":[5.092146915],"iteration":132,"passed_time":0.2543596837,"remaining_time":1.658119141},
{"learn":[5.085258329],"iteration":133,"passed_time":0.2549777202,"remaining_time":1.647841087},
{"learn":[5.079219421],"iteration":134,"passed_time":0.2559166415,"remaining_time":1.639762184},
{"learn":[5.076476829],"iteration":135,"passed_time":0.2566408837,"remaining_time":1.630424438},
{"learn":[5.072133867],"iteration":136,"passed_time":0.2575231141,"remaining_time":1.622207646},
{"learn":[5.067031564],"iteration":137,"passed_time":0.2587586315,"remaining_time":1.616303915},
{"learn":[5.061358312],"iteration":138,"passed_time":0.2595517224,"remaining_time":1.607726856},
{"learn":[5.056759124],"iteration":139,"passed_time":0.2608532655,"remaining_time":1.602384345},
{"learn":[5.050254],"iteration":140,"passed_time":0.2615134584,"remaining_time":1.59319192},
{"learn":[5.048376474],"iteration":141,"passed_time":0.2619828478,"remaining_time":1.582966785},
{"learn":[5.042603751],"iteration":142,"passed_time":0.262590089,"remaining_time":1.57370424},
{"learn":[5.037477349],"iteration":143,"passed_time":0.2632869408,"remaining_time":1.565094592},
{"learn":[5.03230489],"iteration":144,"passed_time":0.2639002235,"remaining_time":1.556101318},
{"learn":[5.025976187],"iteration":145,"passed_time":0.2646371241,"remaining_time":1.547945918},
{"learn":[5.01952451],"iteration":146,"passed_time":0.2652431908,"remaining_time":1.539132257},
{"learn":[5.017569424],"iteration":147,"passed_time":0.2659893195,"remaining_time":1.531235812},
{"learn":[5.008962367],"iteration":148,"passed_time":0.2668285012,"remaining_time":1.523966809},
{"learn":[5.003880266],"iteration":149,"passed_time":0.2675506571,"remaining_time":1.51612039},
{"learn":[4.996387564],"iteration":150,"passed_time":0.2682421864,"remaining_time":1.508196134},
{"learn":[4.993361683],"iteration":151,"passed_time":0.2689143195,"remaining_time":1.500258835},
{"learn":[4.99005752],"iteration":152,"passed_time":0.2695476482,"remaining_time":1.492201687},
{"learn":[4.986908764],"iteration":153,"passed_time":0.2702074932,"remaining_time":1.484386618},
{"learn":[4.985207175],"iteration":154,"passed_time":0.2709358333,"remaining_time":1.477037285},
{"learn":[4.979003494],"iteration":155,"passed_time":0.2718233218,"remaining_time":1.470633869},
{"learn":[4.973142217],"iteration":156,"passed_time":0.2726163247,"remaining_time":1.463793387},
{"learn":[4.967056696],"iteration":157,"passed_time":0.2735945731,"remaining_time":1.458016649},
{"learn":[4.961460696],"iteration":158,"passed_time":0.2744856183,"remaining_time":1.451839025},
{"learn":[4.954240363],"iteration":159,"passed_time":0.2754495022,"remaining_time":1.446109887},
{"learn":[4.952320707],"iteration":160,"passed_time":0.2759310822,"remaining_time":1.437926571},
{"learn":[4.948337777],"iteration":161,"passed_time":0.2766129844,"remaining_time":1.430874574},
{"learn":[4.943228639],"iteration":162,"passed_time":0.2773351359,"remaining_time":1.424107416},
{"learn":[4.938545759],"iteration":163,"passed_time":0.2779918604,"remaining_time":1.417080459},
{"learn":[4.935330572],"iteration":164,"passed_time":0.2786220134,"remaining_time":1.40999625},
{"learn":[4.932051543],"iteration":165,"passed_time":0.279305772,"remaining_time":1.40325912},
{"learn":[4.928964153],"iteration":166,"passed_time":0.280069754,"remaining_time":1.396994641},
{"learn":[4.922860227],"iteration":167,"passed_time":0.2808695023,"remaining_time":1.390972773},
{"learn":[4.917668772],"iteration":168,"passed_time":0.2817816586,"remaining_time":1.385565434},
{"learn":[4.910365386],"iteration":169,"passed_time":0.2826092804,"remaining_time":1.379798251},
{"learn":[4.906457206],"iteration":170,"passed_time":0.2833876797,"remaining_time":1.373850213},
{"learn":[4.901996508],"iteration":171,"passed_time":0.2841340799,"remaining_time":1.367808245},
{"learn":[4.896816173],"iteration":172,"passed_time":0.2848944975,"remaining_time":1.361894505},
{"learn":[4.891123132],"iteration":173,"passed_time":0.2856997253,"remaining_time":1.356252719},
{"learn":[4.887630202],"iteration":174,"passed_time":0.2868880498,"remaining_time":1.352472235},
{"learn":[4.885259712],"iteration":175,"passed_time":0.2879423593,"remaining_time":1.348093773},
{"learn":[4.880659728],"iteration":176,"passed_time":0.2888695447,"remaining_time":1.343161781},
{"learn":[4.877299723],"iteration":177,"passed_time":0.2902241227,"remaining_time":1.340248477},
{"learn":[4.874038772],"iteration":178,"passed_time":0.2910515422,"remaining_time":1.334934727},
{"learn":[4.86943698],"iteration":179,"passed_time":0.291752775,"remaining_time":1.329095975},
{"learn":[4.861268711],"iteration":180,"passed_time":0.2926392069,"remaining_time":1.324151991},
{"learn":[4.858673056],"iteration":181,"passed_time":0.2933847849,"remaining_time":1.318619528},
{"learn":[4.854036207],"iteration":182,"passed_time":0.2943133332,"remaining_time":1.313956247},
{"learn":[4.85130244],"iteration":183,"passed_time":0.2952812306,"remaining_time":1.309508066},
{"learn":[4.847510084],"iteration":184,"passed_time":0.2961467126,"remaining_time":1.304646329},
{"learn":[4.845691673],"iteration":185,"passed_time":0.2969898435,"remaining_time":1.299729745},
{"learn":[4.842058646],"iteration":186,"passed_time":0.2978338893,"remaining_time":1.294860706},
{"learn":[4.838623675],"iteration":187,"passed_time":0.2987213902,"remaining_time":1.290222175},
{"learn":[4.834602161],"iteration":188,"passed_time":0.299499859,"remaining_time":1.28515548},
{"learn":[4.830858976],"iteration":189,"passed_time":0.3002601798,"remaining_time":1.280056556},
{"learn":[4.827590511],"iteration":190,"passed_time":0.3012073901,"remaining_time":1.275794652},
{"learn":[4.822246226],"iteration":191,"passed_time":0.3022226953,"remaining_time":1.271853843},
{"learn":[4.816686395],"iteration":192,"passed_time":0.3031672626,"remaining_time":1.267647569},
{"learn":[4.814797121],"iteration":193,"passed_time":0.3041470018,"remaining_time":1.263621049},
{"learn":[4.811639392],"iteration":194,"passed_time":0.3050723268,"remaining_time":1.259401144},
{"learn":[4.804813432],"iteration":195,"passed_time":0.3060100888,"remaining_time":1.255265874},
{"learn":[4.80251613],"iteration":196,"passed_time":0.306878395,"remaining_time":1.250879955},
{"learn":[4.800087884],"iteration":197,"passed_time":0.3080482102,"remaining_time":1.247750831},
{"learn":[4.794773135],"iteration":198,"passed_time":0.3095611967,"remaining_time":1.246022706},
{"learn":[4.791664833],"iteration":199,"passed_time":0.3103991131,"remaining_time":1.241596452},
{"learn":[4.785989873],"iteration":200,"passed_time":0.3116763922,"remaining_time":1.238952425},
{"learn":[4.782387142],"iteration":201,"passed_time":0.313559788,"remaining_time":1.23871639},
{"learn":[4.778623704],"iteration":202,"passed_time":0.3153920349,"remaining_time":1.238263309},
{"learn":[4.775772178],"iteration":203,"passed_time":0.3169093032,"remaining_time":1.236567673},
{"learn":[4.77023101],"iteration":204,"passed_time":0.3183125431,"remaining_time":1.23443157},
{"learn":[4.764496689],"iteration":205,"passed_time":0.3191607489,"remaining_time":1.230163275},
{"learn":[4.763138716],"iteration":206,"passed_time":0.3200226172,"remaining_time":1.225980365},
{"learn":[4.758053283],"iteration":207,"passed_time":0.3209034691,"remaining_time":1.221901671},
{"learn":[4.755063788],"iteration":208,"passed_time":0.321690994,"remaining_time":1.217500365},
{"learn":[4.752465267],"iteration":209,"passed_time":0.3231264281,"remaining_time":1.215570849},
{"learn":[4.748067377],"iteration":210,"passed_time":0.3246891866,"remaining_time":1.214122124},
{"learn":[4.744163298],"iteration":211,"passed_time":0.3258182699,"remaining_time":1.211060362},
{"learn":[4.736670896],"iteration":212,"passed_time":0.32685136,"remaining_time":1.207662067},
{"learn":[4.73349255],"iteration":213,"passed_time":0.3278011133,"remaining_time":1.20397979},
{"learn":[4.731864595],"iteration":214,"passed_time":0.3287905468,"remaining_time":1.200467811},
{"learn":[4.728398311],"iteration":215,"passed_time":0.3296826359,"remaining_time":1.196625864},
{"learn":[4.723865975],"iteration":216,"passed_time":0.3306933572,"remaining_time":1.193239165},
{"learn":[4.723483365],"iteration":217,"passed_time":0.3319342323,"remaining_time":1.190699861},
{"learn":[4.72095416],"iteration":218,"passed_time":0.3330169568,"remaining_time":1.187608417},
{"learn":[4.716173382],"iteration":219,"passed_time":0.3338793123,"remaining_time":1.183753925},
{"learn":[4.710563974],"iteration":220,"passed_time":0.3348751992,"remaining_time":1.180397195},
{"learn":[4.707160263],"iteration":221,"passed_time":0.3364001595,"remaining_time":1.178915874},
{"learn":[4.70408351],"iteration":222,"passed_time":0.3378277697,"remaining_time":1.177094964},
{"learn":[4.702501831],"iteration":223,"passed_time":0.3391513128,"remaining_time":1.174917048},
{"learn":[4.700269738],"iteration":224,"passed_time":0.3406031745,"remaining_time":1.173188712},
{"learn":[4.695346302],"iteration":225,"passed_time":0.3414141236,"remaining_time":1.169267839},
{"learn":[4.689769299],"iteration":226,"passed_time":0.3422681556,"remaining_time":1.165521076},
{"learn":[4.687919514],"iteration":227,"passed_time":0.343063988,"remaining_time":1.161602626},
{"learn":[4.682982074],"iteration":228,"passed_time":0.3440364044,"remaining_time":1.158305973},
{"learn":[4.679578702],"iteration":229,"passed_time":0.3449143857,"remaining_time":1.154713378},
{"learn":[4.675751423],"iteration":230,"passed_time":0.3458385286,"remaining_time":1.151297959},
{"learn":[4.672710726],"iteration":231,"passed_time":0.3469449092,"remaining_time":1.148507286},
{"learn":[4.6690533],"iteration":232,"passed_time":0.3481770905,"remaining_time":1.146145186},
{"learn":[4.667595702],"iteration":233,"passed_time":0.349907907,"remaining_time":1.145425029},
{"learn":[4.664241291],"iteration":234,"passed_time":0.3507934102,"remaining_time":1.141944506},
{"learn":[4.662246999],"iteration":235,"passed_time":0.3516540717,"remaining_time":1.138405554},
{"learn":[4.658668443],"iteration":236,"passed_time":0.3525002303,"remaining_time":1.134842514},
{"learn":[4.658017572],"iteration":237,"passed_time":0.3532508136,"remaining_time":1.130996302},
{"learn":[4.657656705],"iteration":238,"passed_time":0.3540636018,"remaining_time":1.127374063},
{"learn":[4.653242871],"iteration":239,"passed_time":0.3548239394,"remaining_time":1.123609142},
{"learn":[4.6507302],"iteration":240,"passed_time":0.3556485115,"remaining_time":1.120071453},
{"learn":[4.647671336],"iteration":241,"passed_time":0.3566483288,"remaining_time":1.117105096},
{"learn":[4.645506007],"iteration":242,"passed_time":0.3575341564,"remaining_time":1.113799821},
{"learn":[4.641297906],"iteration":243,"passed_time":0.3585812163,"remaining_time":1.111013932},
{"learn":[4.63798107],"iteration":244,"passed_time":0.3595829232,"remaining_time":1.108102478},
{"learn":[4.635062318],"iteration":245,"passed_time":0.3605952793,"remaining_time":1.10523919},
{"learn":[4.631606017],"iteration":246,"passed_time":0.3618131286,"remaining_time":1.103017352},
{"learn":[4.630215494],"iteration":247,"passed_time":0.3632170863,"remaining_time":1.101367939},
{"learn":[4.62729814],"iteration":248,"passed_time":0.3642392251,"remaining_time":1.098568908},
{"learn":[4.624691756],"iteration":249,"passed_time":0.3651580608,"remaining_time":1.095474182},
{"learn":[4.621840053],"iteration":250,"passed_time":0.3660120141,"remaining_time":1.092203182},
{"learn":[4.619602091],"iteration":251,"passed_time":0.3668851365,"remaining_time":1.089008262},
{"learn":[4.613584029],"iteration":252,"passed_time":0.3677198247,"remaining_time":1.085718218},
{"learn":[4.6119388],"iteration":253,"passed_time":0.3690846585,"remaining_time":1.084004548},
{"learn":[4.60870702],"iteration":254,"passed_time":0.3706102431,"remaining_time":1.082763259},
{"learn":[4.604771557],"iteration":255,"passed_time":0.3725715336,"remaining_time":1.082786019},
{"learn":[4.604231277],"iteration":256,"passed_time":0.3744669151,"remaining_time":1.082602794},
{"learn":[4.600750354],"iteration":257,"passed_time":0.3755019308,"remaining_time":1.07993191},
{"learn":[4.596488253],"iteration":258,"passed_time":0.3766918609,"remaining_time":1.077716868},
{"learn":[4.59470784],"iteration":259,"passed_time":0.3779027788,"remaining_time":1.075569447},
{"learn":[4.588818005],"iteration":260,"passed_time":0.3795458987,"remaining_time":1.074652947},
{"learn":[4.585054174],"iteration":261,"passed_time":0.3805527101,"remaining_time":1.07193855},
{"learn":[4.581471435],"iteration":262,"passed_time":0.3814769026,"remaining_time":1.069005617},
{"learn":[4.577555199],"iteration":263,"passed_time":0.382557224,"remaining_time":1.06652317},
{"learn":[4.57457145],"iteration":264,"passed_time":0.3836066242,"remaining_time":1.063965542},
{"learn":[4.573029224],"iteration":265,"passed_time":0.3851747643,"remaining_time":1.062850665},
{"learn":[4.571326203],"iteration":266,"passed_time":0.3860438279,"remaining_time":1.059813205},
{"learn":[4.571019224],"iteration":267,"passed_time":0.3869538715,"remaining_time":1.056903858},
{"learn":[4.565766631],"iteration":268,"passed_time":0.3877900902,"remaining_time":1.053808758},
{"learn":[4.563383471],"iteration":269,"passed_time":0.3886967609,"remaining_time":1.050920872},
{"learn":[4.558165805],"iteration":270,"passed_time":0.3895729406,"remaining_time":1.047965586},
{"learn":[4.55629209],"iteration":271,"passed_time":0.3904852896,"remaining_time":1.045122393},
{"learn":[4.549383848],"iteration":272,"passed_time":0.3928818126,"remaining_time":1.046245706},
{"learn":[4.546227503],"iteration":273,"passed_time":0.394450393,"remaining_time":1.045149582},
{"learn":[4.540620977],"iteration":274,"passed_time":0.3959388656,"remaining_time":1.043838828},
{"learn":[4.532898237],"iteration":275,"passed_time":0.3970951554,"remaining_time":1.041655408},
{"learn":[4.529757367],"iteration":276,"passed_time":0.3979335013,"remaining_time":1.038649536},
{"learn":[4.52579294],"iteration":277,"passed_time":0.3987552276,"remaining_time":1.035616095},
{"learn":[4.521572155],"iteration":278,"passed_time":0.3995961673,"remaining_time":1.03264816},
{"learn":[4.518818099],"iteration":279,"passed_time":0.4005041273,"remaining_time":1.029867756},
{"learn":[4.514012334],"iteration":280,"passed_time":0.4014794995,"remaining_time":1.027273168},
{"learn":[4.508331416],"iteration":281,"passed_time":0.402371435,"remaining_time":1.024477625},
{"learn":[4.506038537],"iteration":282,"passed_time":0.4032800009,"remaining_time":1.02173767},
{"learn":[4.505805643],"iteration":283,"passed_time":0.4041264446,"remaining_time":1.018853994},
{"learn":[4.501550352],"iteration":284,"passed_time":0.4050295908,"remaining_time":1.016126868},
{"learn":[4.494692643],"iteration":285,"passed_time":0.405955473,"remaining_time":1.013469258},
{"learn":[4.489330245],"iteration":286,"passed_time":0.4073393658,"remaining_time":1.01196156},
{"learn":[4.484826955],"iteration":287,"passed_time":0.4088065126,"remaining_time":1.010660545},
{"learn":[4.478285428],"iteration":288,"passed_time":0.4098502056,"remaining_time":1.008316596},
{"learn":[4.475311671],"iteration":289,"passed_time":0.4110457953,"remaining_time":1.006353499},
{"learn":[4.471581298],"iteration":290,"passed_time":0.411929253,"remaining_time":1.00363519},
{"learn":[4.469164956],"iteration":291,"passed_time":0.4127910262,"remaining_time":1.000876872},
{"learn":[4.462068024],"iteration":292,"passed_time":0.4136925856,"remaining_time":0.9982275018},
{"learn":[4.458540976],"iteration":293,"passed_time":0.4146192795,"remaining_time":0.9956503787},
{"learn":[4.455757458],"iteration":294,"passed_time":0.4155151366,"remaining_time":0.9930107501},
{"learn":[4.453027414],"iteration":295,"passed_time":0.4163090385,"remaining_time":0.9901404159},
{"learn":[4.450659338],"iteration":296,"passed_time":0.4171020194,"remaining_time":0.9872818843},
{"learn":[4.444696901],"iteration":297,"passed_time":0.4178632404,"remaining_time":0.9843623986},
{"learn":[4.442052813],"iteration":298,"passed_time":0.4186140969,"remaining_time":0.9814330499},
{"learn":[4.440036756],"iteration":299,"passed_time":0.4193764672,"remaining_time":0.9785450902},
{"learn":[4.435017051],"iteration":300,"passed_time":0.4202051752,"remaining_time":0.9758253072},
{"learn":[4.429962125],"iteration":301,"passed_time":0.4213175181,"remaining_time":0.9737736015},
{"learn":[4.427666256],"iteration":302,"passed_time":0.4222551957,"remaining_time":0.9713263082},
{"learn":[4.425030004],"iteration":303,"passed_time":0.4233783511,"remaining_time":0.9693135932},
{"learn":[4.422588771],"iteration":304,"passed_time":0.4243676354,"remaining_time":0.9670016611},
{"learn":[4.418936667],"iteration":305,"passed_time":0.425314351,"remaining_time":0.9646018288},
{"learn":[4.416887976],"iteration":306,"passed_time":0.4262394829,"remaining_time":0.9621627416},
{"learn":[4.413773354],"iteration":307,"passed_time":0.4270306298,"remaining_time":0.9594324541},
{"learn":[4.411129391],"iteration":308,"passed_time":0.4279097265,"remaining_time":0.9569113949},
{"learn":[4.40850819],"iteration":309,"passed_time":0.4289411262,"remaining_time":0.954739926},
{"learn":[4.404880292],"iteration":310,"passed_time":0.4304400145,"remaining_time":0.953611479},
{"learn":[4.404593827],"iteration":311,"passed_time":0.4316210177,"remaining_time":0.9517796801},
{"learn":[4.402139942],"iteration":312,"passed_time":0.4333339532,"remaining_time":0.9511195715},
{"learn":[4.400284725],"iteration":313,"passed_time":0.4347129431,"remaining_time":0.9497231815},
{"learn":[4.395805521],"iteration":314,"passed_time":0.4356063239,"remaining_time":0.9472708948},
{"learn":[4.392838833],"iteration":315,"passed_time":0.4367562139,"remaining_time":0.9453837035},
{"learn":[4.389213061],"iteration":316,"passed_time":0.4379558955,"remaining_time":0.9436084435},
{"learn":[4.3861981],"iteration":317,"passed_time":0.4393420746,"remaining_time":0.9422367764},
{"learn":[4.385054234],"iteration":318,"passed_time":0.440269504,"remaining_time":0.9398856809},
{"learn":[4.379364607],"iteration":319,"passed_time":0.4412333827,"remaining_time":0.9376209382},
{"learn":[4.378387619],"iteration":320,"passed_time":0.4424548147,"remaining_time":0.9359090941},
{"learn":[4.375816727],"iteration":321,"passed_time":0.4437781071,"remaining_time":0.9344147721},
{"learn":[4.374600202],"iteration":322,"passed_time":0.4451243769,"remaining_time":0.9329696693},
{"learn":[4.37098897],"iteration":323,"passed_time":0.4461646866,"remaining_time":0.9308868153},
{"learn":[4.367418484],"iteration":324,"passed_time":0.4472955183,"remaining_time":0.9289983842},
{"learn":[4.363584638],"iteration":325,"passed_time":0.4482047865,"remaining_time":0.9266565217},
{"learn":[4.360770706],"iteration":326,"passed_time":0.4491907364,"remaining_time":0.9244812403},
{"learn":[4.358675808],"iteration":327,"passed_time":0.4504727201,"remaining_time":0.9229197192},
{"learn":[4.354228195],"iteration":328,"passed_time":0.4515999506,"remaining_time":0.9210442761},
{"learn":[4.353773425],"iteration":329,"passed_time":0.4528109989,"remaining_time":0.9193435432},
{"learn":[4.351648009],"iteration":330,"passed_time":0.4546372035,"remaining_time":0.918889091},
{"learn":[4.348209927],"iteration":331,"passed_time":0.4561914038,"remaining_time":0.9178790896},
{"learn":[4.345852733],"iteration":332,"passed_time":0.4571140106,"remaining_time":0.915600736},
{"learn":[4.34237339],"iteration":333,"passed_time":0.4581701721,"remaining_time":0.9135968103},
{"learn":[4.340814362],"iteration":334,"passed_time":0.4593115343,"remaining_time":0.9117676726},
{"learn":[4.339707068],"iteration":335,"passed_time":0.4605787093,"remaining_time":0.9101912588},
{"learn":[4.335430786],"iteration":336,"passed_time":0.4618014719,"remaining_time":0.9085293052},
{"learn":[4.33521887],"iteration":337,"passed_time":0.4626777515,"remaining_time":0.9061913358},
{"learn":[4.328507238],"iteration":338,"passed_time":0.4635904173,"remaining_time":0.9039329376},
{"learn":[4.326140732],"iteration":339,"passed_time":0.4647527038,"remaining_time":0.9021670132},
{"learn":[4.323785636],"iteration":340,"passed_time":0.4656425073,"remaining_time":0.899878042},
{"learn":[4.320632534],"iteration":341,"passed_time":0.4672678694,"remaining_time":0.8990124506},
{"learn":[4.31973724],"iteration":342,"passed_time":0.46823247,"remaining_time":0.8968767719},
{"learn":[4.318000924],"iteration":343,"passed_time":0.4692423607,"remaining_time":0.8948342692},
{"learn":[4.312713628],"iteration":344,"passed_time":0.4704345339,"remaining_time":0.8931438252},
{"learn":[4.308220789],"iteration":345,"passed_time":0.4720757926,"remaining_time":0.8923051108},
{"learn":[4.305890947],"iteration":346,"passed_time":0.4737066447,"remaining_time":0.8914421872},
{"learn":[4.305137856],"iteration":347,"passed_time":0.4746559465,"remaining_time":0.8892979228},
{"learn":[4.304787172],"iteration":348,"passed_time":0.4755058519,"remaining_time":0.8869750991},
{"learn":[4.30350134],"iteration":349,"passed_time":0.4763575817,"remaining_time":0.8846640803},
{"learn":[4.30293809],"iteration":350,"passed_time":0.477304061,"remaining_time":0.8825365685},
{"learn":[4.299548459],"iteration":351,"passed_time":0.4781682608,"remaining_time":0.8802642984},
{"learn":[4.294768408],"iteration":352,"passed_time":0.4791544875,"remaining_time":0.878223664},
{"learn":[4.294581479],"iteration":353,"passed_time":0.480117981,"remaining_time":0.8761475021},
{"learn":[4.292551604],"iteration":354,"passed_time":0.4809632742,"remaining_time":0.8738628504},
{"learn":[4.288628894],"iteration":355,"passed_time":0.4819589016,"remaining_time":0.8718582378},
{"learn":[4.287802767],"iteration":356,"passed_time":0.4834988307,"remaining_time":0.8708396306},
{"learn":[4.284566905],"iteration":357,"passed_time":0.4849146454,"remaining_time":0.8695955373},
{"learn":[4.27890232],"iteration":358,"passed_time":0.4861962472,"remaining_time":0.8681108481},
{"learn":[4.276938023],"iteration":359,"passed_time":0.4875017527,"remaining_time":0.8666697825},
{"learn":[4.273425094],"iteration":360,"passed_time":0.4890309904,"remaining_time":0.8656254927},
{"learn":[4.269726505],"iteration":361,"passed_time":0.4901414729,"remaining_time":0.8638404965},
{"learn":[4.265565857],"iteration":362,"passed_time":0.4932889723,"remaining_time":0.8656338164},
{"learn":[4.262117173],"iteration":363,"passed_time":0.4948140026,"remaining_time":0.8645651254},
{"learn":[4.259185148],"iteration":364,"passed_time":0.4957130349,"remaining_time":0.8624048689},
{"learn":[4.257668507],"iteration":365,"passed_time":0.496647308,"remaining_time":0.8603125499},
{"learn":[4.253432436],"iteration":366,"passed_time":0.4978220354,"remaining_time":0.8586412763},
{"learn":[4.250216667],"iteration":367,"passed_time":0.4995172536,"remaining_time":0.8578665876},
{"learn":[4.24514828],"iteration":368,"passed_time":0.5006074385,"remaining_time":0.8560522864},
{"learn":[4.244015772],"iteration":369,"passed_time":0.5016568086,"remaining_time":0.8541724039},
{"learn":[4.240329192],"iteration":370,"passed_time":0.5027228716,"remaining_time":0.8523252998},
{"learn":[4.236718014],"iteration":371,"passed_time":0.5039395571,"remaining_time":0.8507366716},
{"learn":[4.233495944],"iteration":372,"passed_time":0.5056902264,"remaining_time":0.850047646},
{"learn":[4.230357491],"iteration":373,"passed_time":0.5074599468,"remaining_time":0.8493848308},
{"learn":[4.227381215],"iteration":374,"passed_time":0.5087996145,"remaining_time":0.8479993574},
{"learn":[4.226169067],"iteration":375,"passed_time":0.5096478518,"remaining_time":0.8457985626},
{"learn":[4.225963861],"iteration":376,"passed_time":0.5105693541,"remaining_time":0.8437260148},
{"learn":[4.224346548],"iteration":377,"passed_time":0.5114577019,"remaining_time":0.8416050016},
{"learn":[4.222595381],"iteration":378,"passed_time":0.5126031341,"remaining_time":0.8399117316},
{"learn":[4.219700938],"iteration":379,"passed_time":0.5139146966,"remaining_time":0.8384923997},
{"learn":[4.216356207],"iteration":380,"passed_time":0.5155872813,"remaining_time":0.8376601761},
{"learn":[4.214326494],"iteration":381,"passed_time":0.5164766689,"remaining_time":0.8355564958},
{"learn":[4.212901398],"iteration":382,"passed_time":0.5175457868,"remaining_time":0.8337486957},
{"learn":[4.211331091],"iteration":383,"passed_time":0.51837809,"remaining_time":0.8315648527},
{"learn":[4.208624791],"iteration":384,"passed_time":0.5194677894,"remaining_time":0.829799196},
{"learn":[4.204659106],"iteration":385,"passed_time":0.5203894108,"remaining_time":0.8277696846},
{"learn":[4.202968852],"iteration":386,"passed_time":0.5213070639,"remaining_time":0.8257396129},
{"learn":[4.197261935],"iteration":387,"passed_time":0.5221305387,"remaining_time":0.8235667259},
{"learn":[4.196934403],"iteration":388,"passed_time":0.5228751837,"remaining_time":0.8212769594},
{"learn":[4.192479929],"iteration":389,"passed_time":0.5238031389,"remaining_time":0.8192818327},
{"learn":[4.190243116],"iteration":390,"passed_time":0.5247511191,"remaining_time":0.8173233542},
{"learn":[4.185852431],"iteration":391,"passed_time":0.5256276935,"remaining_time":0.8152592797},
{"learn":[4.180967944],"iteration":392,"passed_time":0.5265194578,"remaining_time":0.8132247096},
{"learn":[4.178283162],"iteration":393,"passed_time":0.5278926098,"remaining_time":0.811936349},
{"learn":[4.176341157],"iteration":394,"passed_time":0.5293210753,"remaining_time":0.81073228},
{"learn":[4.176041504],"iteration":395,"passed_time":0.5303075839,"remaining_time":0.8088529815},
{"learn":[4.175564513],"iteration":396,"passed_time":0.5312921349,"remaining_time":0.8069752075},
{"learn":[4.170830274],"iteration":397,"passed_time":0.5322891628,"remaining_time":0.805120794},
{"learn":[4.167804808],"iteration":398,"passed_time":0.5333427341,"remaining_time":0.8033558476},
{"learn":[4.165860548],"iteration":399,"passed_time":0.5346008702,"remaining_time":0.8019013053},
{"learn":[4.160950571],"iteration":400,"passed_time":0.5361999864,"remaining_time":0.8009570869},
{"learn":[4.158544115],"iteration":401,"passed_time":0.5371432919,"remaining_time":0.7990340512},
{"learn":[4.154448767],"iteration":402,"passed_time":0.5380940994,"remaining_time":0.797126991},
{"learn":[4.15197457],"iteration":403,"passed_time":0.5389863589,"remaining_time":0.7951382918},
{"learn":[4.149562679],"iteration":404,"passed_time":0.5399267982,"remaining_time":0.79322579},
{"learn":[4.149327961],"iteration":405,"passed_time":0.5409449295,"remaining_time":0.7914317442},
{"learn":[4.147444889],"iteration":406,"passed_time":0.5420221777,"remaining_time":0.7897276446},
{"learn":[4.147254809],"iteration":407,"passed_time":0.5433162232,"remaining_time":0.7883411866},
{"learn":[4.144589165],"iteration":408,"passed_time":0.5445113041,"remaining_time":0.7868121779},
{"learn":[4.141691034],"iteration":409,"passed_time":0.5459231769,"remaining_time":0.7855967668},
{"learn":[4.138893468],"iteration":410,"passed_time":0.5467643234,"remaining_time":0.7835624976},
{"learn":[4.136964597],"iteration":411,"passed_time":0.5478175259,"remaining_time":0.7818366632},
{"learn":[4.133773523],"iteration":412,"passed_time":0.5488050947,"remaining_time":0.7800208004},
{"learn":[4.131363444],"iteration":413,"passed_time":0.5498265853,"remaining_time":0.7782569541},
{"learn":[4.130228592],"iteration":414,"passed_time":0.5507862753,"remaining_time":0.7764095688},
{"learn":[4.12884186],"iteration":415,"passed_time":0.5516232239,"remaining_time":0.7743941412},
{"learn":[4.12413494],"iteration":416,"passed_time":0.5524986273,"remaining_time":0.7724381289},
{"learn":[4.119422508],"iteration":417,"passed_time":0.5534459028,"remaining_time":0.7705873575},
{"learn":[4.117038244],"iteration":418,"passed_time":0.5543954034,"remaining_time":0.7687439842},
{"learn":[4.116067631],"iteration":419,"passed_time":0.555390383,"remaining_time":0.7669676717},
{"learn":[4.110343455],"iteration":420,"passed_time":0.5563416712,"remaining_time":0.7651349825},
{"learn":[4.105604544],"iteration":421,"passed_time":0.557623379,"remaining_time":0.7637590357},
{"learn":[4.103390131],"iteration":422,"passed_time":0.5590071107,"remaining_time":0.7625227018},
{"learn":[4.096724402],"iteration":423,"passed_time":0.5602649084,"remaining_time":0.7611145926},
{"learn":[4.093431279],"iteration":424,"passed_time":0.5611692764,"remaining_time":0.759229021},
{"learn":[4.091412744],"iteration":425,"passed_time":0.5620958268,"remaining_time":0.757377945},
{"learn":[4.091192901],"iteration":426,"passed_time":0.5628946209,"remaining_time":0.7553597606},
{"learn":[4.088994581],"iteration":427,"passed_time":0.5638535014,"remaining_time":0.7535612215},
{"learn":[4.087845355],"iteration":428,"passed_time":0.564803883,"remaining_time":0.7517552849},
{"learn":[4.083650279],"iteration":429,"passed_time":0.565678773,"remaining_time":0.7498532573},
{"learn":[4.079840652],"iteration":430,"passed_time":0.5666243573,"remaining_time":0.7480493255},
{"learn":[4.075707828],"iteration":431,"passed_time":0.5676200667,"remaining_time":0.7463152728},
{"learn":[4.071345409],"iteration":432,"passed_time":0.5685199624,"remaining_time":0.7444591655},
{"learn":[4.067460475],"iteration":433,"passed_time":0.5694241976,"remaining_time":0.7426131241},
{"learn":[4.064914749],"iteration":434,"passed_time":0.5703351538,"remaining_time":0.7407801423},
{"learn":[4.063823175],"iteration":435,"passed_time":0.5713173173,"remaining_time":0.7390435022},
{"learn":[4.058898471],"iteration":436,"passed_time":0.5723844396,"remaining_time":0.73741977},
{"learn":[4.054120355],"iteration":437,"passed_time":0.5738548069,"remaining_time":0.7363159851},
{"learn":[4.052715901],"iteration":438,"passed_time":0.5751007792,"remaining_time":0.7349237748},
{"learn":[4.052114167],"iteration":439,"passed_time":0.5760677785,"remaining_time":0.7331771726},
{"learn":[4.051377267],"iteration":440,"passed_time":0.5770636478,"remaining_time":0.731470701},
{"learn":[4.049275336],"iteration":441,"passed_time":0.577978018,"remaining_time":0.7296645567},
{"learn":[4.047099198],"iteration":442,"passed_time":0.5788452469,"remaining_time":0.7278031659},
{"learn":[4.044348685],"iteration":443,"passed_time":0.5797414118,"remaining_time":0.7259824887},
{"learn":[4.042822379],"iteration":444,"passed_time":0.580689222,"remaining_time":0.724230378},
{"learn":[4.041258611],"iteration":445,"passed_time":0.5816947852,"remaining_time":0.7225536121},
{"learn":[4.040044254],"iteration":446,"passed_time":0.5824871079,"remaining_time":0.7206160418},
{"learn":[4.036860137],"iteration":447,"passed_time":0.5836267589,"remaining_time":0.7191115422},
{"learn":[4.036372284],"iteration":448,"passed_time":0.584663193,"remaining_time":0.717482003},
{"learn":[4.03368231],"iteration":449,"passed_time":0.5855397591,"remaining_time":0.7156597055},
{"learn":[4.032439519],"iteration":450,"passed_time":0.586619553,"remaining_time":0.7140889903},
{"learn":[4.032008634],"iteration":451,"passed_time":0.5876984728,"remaining_time":0.7125193873},
{"learn":[4.030034932],"iteration":452,"passed_time":0.5892505564,"remaining_time":0.7115232987},
{"learn":[4.028173412],"iteration":453,"passed_time":0.5901956587,"remaining_time":0.709794779},
{"learn":[4.023806097],"iteration":454,"passed_time":0.5911147047,"remaining_time":0.7080384925},
{"learn":[4.020239186],"iteration":455,"passed_time":0.5920648976,"remaining_time":0.7063230357},
{"learn":[4.017384838],"iteration":456,"passed_time":0.5929327039,"remaining_time":0.7045130376},
{"learn":[4.016468229],"iteration":457,"passed_time":0.5937854183,"remaining_time":0.7026892941},
{"learn":[4.014530169],"iteration":458,"passed_time":0.5948486194,"remaining_time":0.7011178717},
{"learn":[4.012884822],"iteration":459,"passed_time":0.5957273665,"remaining_time":0.6993321259},
{"learn":[4.008924707],"iteration":460,"passed_time":0.5966524348,"remaining_time":0.6976044737},
{"learn":[4.008286778],"iteration":461,"passed_time":0.597518905,"remaining_time":0.6958120583},
{"learn":[4.006444202],"iteration":462,"passed_time":0.5984783399,"remaining_time":0.6941314655},
{"learn":[4.003284363],"iteration":463,"passed_time":0.5994969927,"remaining_time":0.6925223881},
{"learn":[3.999811484],"iteration":464,"passed_time":0.6003740766,"remaining_time":0.6907529698},
{"learn":[3.997483319],"iteration":465,"passed_time":0.6013721635,"remaining_time":0.6891260414},
{"learn":[3.99708333],"iteration":466,"passed_time":0.6024577302,"remaining_time":0.6876016492},
{"learn":[3.995860263],"iteration":467,"passed_time":0.6039867932,"remaining_time":0.6865832777},
{"learn":[3.994131111],"iteration":468,"passed_time":0.6050631979,"remaining_time":0.6850502304},
{"learn":[3.993125499],"iteration":469,"passed_time":0.6060877806,"remaining_time":0.6834606887},
{"learn":[3.992954084],"iteration":470,"passed_time":0.6077438328,"remaining_time":0.6825827762},
{"learn":[3.990635743],"iteration":471,"passed_time":0.6088730449,"remaining_time":0.6811122197},
{"learn":[3.986678254],"iteration":472,"passed_time":0.6106242757,"remaining_time":0.6803361381},
{"learn":[3.986393291],"iteration":473,"passed_time":0.6116763757,"remaining_time":0.6787801131},
{"learn":[3.986152671],"iteration":474,"passed_time":0.6126727013,"remaining_time":0.6771645646},
{"learn":[3.985596662],"iteration":475,"passed_time":0.61360904,"remaining_time":0.6754855818},
{"learn":[3.983853457],"iteration":476,"passed_time":0.6146258148,"remaining_time":0.673897906},
{"learn":[3.983263928],"iteration":477,"passed_time":0.6155752414,"remaining_time":0.6722390712},
{"learn":[3.980067202],"iteration":478,"passed_time":0.6166661538,"remaining_time":0.67073709},
{"learn":[3.978115407],"iteration":479,"passed_time":0.6180535119,"remaining_time":0.6695579712},
{"learn":[3.972661644],"iteration":480,"passed_time":0.6193286835,"remaining_time":0.6682569371},
{"learn":[3.969938254],"iteration":481,"passed_time":0.6205309701,"remaining_time":0.6668776816},
{"learn":[3.968211434],"iteration":482,"passed_time":0.6216493221,"remaining_time":0.6654093158},
{"learn":[3.966113368],"iteration":483,"passed_time":0.6229428397,"remaining_time":0.6641291432},
{"learn":[3.962246044],"iteration":484,"passed_time":0.6239969925,"remaining_time":0.6625947446},
{"learn":[3.961319703],"iteration":485,"passed_time":0.6250483086,"remaining_time":0.6610593223},
{"learn":[3.96078191],"iteration":486,"passed_time":0.6260362917,"remaining_time":0.6594591738},
{"learn":[3.958913633],"iteration":487,"passed_time":0.6270338958,"remaining_time":0.6578716284},
{"learn":[3.957428286],"iteration":488,"passed_time":0.6279389325,"remaining_time":0.6561897638},
{"learn":[3.952641965],"iteration":489,"passed_time":0.6289129134,"remaining_time":0.6545828282},
{"learn":[3.951486786],"iteration":490,"passed_time":0.629934402,"remaining_time":0.6530277202},
{"learn":[3.94938344],"iteration":491,"passed_time":0.6310002545,"remaining_time":0.651520588},
{"learn":[3.947297924],"iteration":492,"passed_time":0.6325051164,"remaining_time":0.6504667221},
{"learn":[3.946284886],"iteration":493,"passed_time":0.6340707754,"remaining_time":0.6494733044},
{"learn":[3.943288204],"iteration":494,"passed_time":0.6351020171,"remaining_time":0.6479323609},
{"learn":[3.943076488],"iteration":495,"passed_time":0.6361518984,"remaining_time":0.6464124128},
{"learn":[3.942347078],"iteration":496,"passed_time":0.6372469646,"remaining_time":0.6449400869},
{"learn":[3.940251541],"iteration":497,"passed_time":0.6382241012,"remaining_time":0.6433503992},
{"learn":[3.939011019],"iteration":498,"passed_time":0.6392627617,"remaining_time":0.6418249371},
{"learn":[3.938760512],"iteration":499,"passed_time":0.6402768195,"remaining_time":0.6402768195},
{"learn":[3.934522727],"iteration":500,"passed_time":0.641165916,"remaining_time":0.6386063714},
{"learn":[3.930091193],"iteration":501,"passed_time":0.6422302981,"remaining_time":0.6371129252},
{"learn":[3.927671752],"iteration":502,"passed_time":0.6431242787,"remaining_time":0.6354528162},
{"learn":[3.927280041],"iteration":503,"passed_time":0.6440196243,"remaining_time":0.6337970905},
{"learn":[3.925987561],"iteration":504,"passed_time":0.6448690518,"remaining_time":0.6320993676},
{"learn":[3.921645957],"iteration":505,"passed_time":0.6460189801,"remaining_time":0.6306983719},
{"learn":[3.920333743],"iteration":506,"passed_time":0.6475390251,"remaining_time":0.629658263},
{"learn":[3.918659461],"iteration":507,"passed_time":0.6487304132,"remaining_time":0.6282979593},
{"learn":[3.916124385],"iteration":508,"passed_time":0.6499420574,"remaining_time":0.6269578589},
{"learn":[3.913849268],"iteration":509,"passed_time":0.6508523593,"remaining_time":0.6253287374},
{"learn":[3.912826119],"iteration":510,"passed_time":0.6518621896,"remaining_time":0.6237976727},
{"learn":[3.910034145],"iteration":511,"passed_time":0.6527845121,"remaining_time":0.6221852381},
{"learn":[3.90792379],"iteration":512,"passed_time":0.6542840991,"remaining_time":0.6211235015},
{"learn":[3.907823851],"iteration":513,"passed_time":0.6554140966,"remaining_time":0.6197106049},
{"learn":[3.904527401],"iteration":514,"passed_time":0.6563410205,"remaining_time":0.618107563},
{"learn":[3.903378283],"iteration":515,"passed_time":0.6573187757,"remaining_time":0.6165548207},
{"learn":[3.902170135],"iteration":516,"passed_time":0.658134267,"remaining_time":0.6148527098},
{"learn":[3.899435429],"iteration":517,"passed_time":0.6589582356,"remaining_time":0.6131619103},
{"learn":[3.897497505],"iteration":518,"passed_time":0.6598296447,"remaining_time":0.6115184183},
{"learn":[3.896426119],"iteration":519,"passed_time":0.6608553968,"remaining_time":0.6100203663},
{"learn":[3.896044669],"iteration":520,"passed_time":0.6618750958,"remaining_time":0.6085185622},
{"learn":[3.892795942],"iteration":521,"passed_time":0.6629079859,"remaining_time":0.6070306844},
{"learn":[3.892413888],"iteration":522,"passed_time":0.6642515423,"remaining_time":0.6058278885},
{"learn":[3.891738985],"iteration":523,"passed_time":0.6654059213,"remaining_time":0.6044527071},
{"learn":[3.88822057],"iteration":524,"passed_time":0.6665084551,"remaining_time":0.6030314594},
{"learn":[3.883837053],"iteration":525,"passed_time":0.6681262233,"remaining_time":0.6020757221},
{"learn":[3.881769742],"iteration":526,"passed_time":0.6693133988,"remaining_time":0.6007310012},
{"learn":[3.880356898],"iteration":527,"passed_time":0.6703673963,"remaining_time":0.599267824},
{"learn":[3.879250273],"iteration":528,"passed_time":0.6714057957,"remaining_time":0.5977923058},
{"learn":[3.877174493],"iteration":529,"passed_time":0.6723197756,"remaining_time":0.5962081029},
{"learn":[3.875854201],"iteration":530,"passed_time":0.6732361713,"remaining_time":0.5946285581},
{"learn":[3.873189396],"iteration":531,"passed_time":0.6741502728,"remaining_time":0.5930494881},
{"learn":[3.871583368],"iteration":532,"passed_time":0.6750432617,"remaining_time":0.591454415},
{"learn":[3.869622679],"iteration":533,"passed_time":0.6759299815,"remaining_time":0.5898565007},
{"learn":[3.866860164],"iteration":534,"passed_time":0.6768711839,"remaining_time":0.5883085991},
{"learn":[3.864498444],"iteration":535,"passed_time":0.6778674979,"remaining_time":0.5868106698},
{"learn":[3.861416322],"iteration":536,"passed_time":0.6794646429,"remaining_time":0.5858326437},
{"learn":[3.860265769],"iteration":537,"passed_time":0.6803770348,"remaining_time":0.5842642938},
{"learn":[3.859328725],"iteration":538,"passed_time":0.6815920754,"remaining_time":0.5829572296},
{"learn":[3.858521278],"iteration":539,"passed_time":0.6825775107,"remaining_time":0.5814549165},
{"learn":[3.85599111],"iteration":540,"passed_time":0.6835361173,"remaining_time":0.579931752},
{"learn":[3.852379816],"iteration":541,"passed_time":0.6844404797,"remaining_time":0.5783648334},
{"learn":[3.851327537],"iteration":542,"passed_time":0.6853766276,"remaining_time":0.5768271064},
{"learn":[3.847854898],"iteration":543,"passed_time":0.6862405543,"remaining_time":0.5752310529},
{"learn":[3.847083414],"iteration":544,"passed_time":0.6870272466,"remaining_time":0.5735732059},
{"learn":[3.845397429],"iteration":545,"passed_time":0.6879353474,"remaining_time":0.5720195013},
{"learn":[3.841933528],"iteration":546,"passed_time":0.6890303236,"remaining_time":0.5706229188},
{"learn":[3.840996474],"iteration":547,"passed_time":0.6903340335,"remaining_time":0.5693996042},
{"learn":[3.838355966],"iteration":548,"passed_time":0.6915352899,"remaining_time":0.568091832},
{"learn":[3.83342799],"iteration":549,"passed_time":0.6928452636,"remaining_time":0.5668733975},
{"learn":[3.828161535],"iteration":550,"passed_time":0.6944852841,"remaining_time":0.56592358},
{"learn":[3.823502399],"iteration":551,"passed_time":0.695623519,"remaining_time":0.5645640154},
{"learn":[3.820068862],"iteration":552,"passed_time":0.696925686,"remaining_time":0.5633377606},
{"learn":[3.817951642],"iteration":553,"passed_time":0.6982490959,"remaining_time":0.5621283335},
{"learn":[3.815785958],"iteration":554,"passed_time":0.6995410155,"remaining_time":0.5608932467},
{"learn":[3.81503012],"iteration":555,"passed_time":0.7010054673,"remaining_time":0.5597957329},
{"learn":[3.813529315],"iteration":556,"passed_time":0.7023610003,"remaining_time":0.5586102749},
{"learn":[3.808881326],"iteration":557,"passed_time":0.7034396553,"remaining_time":0.5572048882},
{"learn":[3.808740434],"iteration":558,"passed_time":0.7046052471,"remaining_time":0.5558692557},
{"learn":[3.80714352],"iteration":559,"passed_time":0.7056980562,"remaining_time":0.5544770442},
{"learn":[3.80573346],"iteration":560,"passed_time":0.706836821,"remaining_time":0.5531218617},
{"learn":[3.803370052],"iteration":561,"passed_time":0.7080506127,"remaining_time":0.5518259224},
{"learn":[3.803215211],"iteration":562,"passed_time":0.7096551433,"remaining_time":0.550833566},
{"learn":[3.801309667],"iteration":563,"passed_time":0.7109349255,"remaining_time":0.5495879921},
{"learn":[3.800003847],"iteration":564,"passed_time":0.7123169596,"remaining_time":0.548421022},
{"learn":[3.798026138],"iteration":565,"passed_time":0.7139226308,"remaining_time":0.5474247734},
{"learn":[3.794745847],"iteration":566,"passed_time":0.7149289467,"remaining_time":0.5459686665},
{"learn":[3.794312041],"iteration":567,"passed_time":0.7159670145,"remaining_time":0.5445382927},
{"learn":[3.792205926],"iteration":568,"passed_time":0.7170872964,"remaining_time":0.5431715725},
{"learn":[3.788991061],"iteration":569,"passed_time":0.7183177082,"remaining_time":0.5418887974},
{"learn":[3.787391572],"iteration":570,"passed_time":0.7195311032,"remaining_time":0.5405934208},
{"learn":[3.7826445],"iteration":571,"passed_time":0.7205483195,"remaining_time":0.5391515398},
{"learn":[3.781700331],"iteration":572,"passed_time":0.7216934677,"remaining_time":0.5378064759},
{"learn":[3.780045374],"iteration":573,"passed_time":0.7229418135,"remaining_time":0.5365386978},
{"learn":[3.775462644],"iteration":574,"passed_time":0.7245409365,"remaining_time":0.5355302574},
{"learn":[3.773711943],"iteration":575,"passed_time":0.7260295107,"remaining_time":0.5344383898},
{"learn":[3.772415806],"iteration":576,"passed_time":0.7274118499,"remaining_time":0.533267266},
{"learn":[3.770170875],"iteration":577,"passed_time":0.7284681629,"remaining_time":0.5318573785},
{"learn":[3.765166479],"iteration":578,"passed_time":0.7295340375,"remaining_time":0.5304556646},
{"learn":[3.763976102],"iteration":579,"passed_time":0.7305478657,"remaining_time":0.52901742},
{"learn":[3.760761708],"iteration":580,"passed_time":0.7314688569,"remaining_time":0.5275136851},
{"learn":[3.758155662],"iteration":581,"passed_time":0.7327213071,"remaining_time":0.5262500109},
{"learn":[3.756844548],"iteration":582,"passed_time":0.7339258752,"remaining_time":0.5249521268},
{"learn":[3.753098923],"iteration":583,"passed_time":0.7349811165,"remaining_time":0.5235481925},
{"learn":[3.751618946],"iteration":584,"passed_time":0.7360634503,"remaining_time":0.5221646698},
{"learn":[3.751398464],"iteration":585,"passed_time":0.7373558649,"remaining_time":0.520930594},
{"learn":[3.749920103],"iteration":586,"passed_time":0.738706533,"remaining_time":0.5197373052},
{"learn":[3.748237465],"iteration":587,"passed_time":0.7402535613,"remaining_time":0.5186810667},
{"learn":[3.746021536],"iteration":588,"passed_time":0.7414911498,"remaining_time":0.517407237},
{"learn":[3.74417648],"iteration":589,"passed_time":0.7427418732,"remaining_time":0.5161426576},
{"learn":[3.738788389],"iteration":590,"passed_time":0.7441243823,"remaining_time":0.5149693272},
{"learn":[3.736021611],"iteration":591,"passed_time":0.7453642816,"remaining_time":0.5136970049},
{"learn":[3.734546151],"iteration":592,"passed_time":0.7472222025,"remaining_time":0.5128489653},
{"learn":[3.733527479],"iteration":593,"passed_time":0.7484255353,"remaining_time":0.5115501133},
{"learn":[3.733026392],"iteration":594,"passed_time":0.7494891023,"remaining_time":0.5101564478},
{"learn":[3.730314752],"iteration":595,"passed_time":0.7505104658,"remaining_time":0.5087352822},
{"learn":[3.727342596],"iteration":596,"passed_time":0.7516790905,"remaining_time":0.5074148634},
{"learn":[3.725459604],"iteration":597,"passed_time":0.7528804789,"remaining_time":0.5061169774},
{"learn":[3.723158842],"iteration":598,"passed_time":0.7546554254,"remaining_time":0.5052033816},
{"learn":[3.722362756],"iteration":599,"passed_time":0.756205353,"remaining_time":0.504136902},
{"learn":[3.721443615],"iteration":600,"passed_time":0.7575688559,"remaining_time":0.5029450474},
{"learn":[3.720743486],"iteration":601,"passed_time":0.7586739308,"remaining_time":0.5015817682},
{"learn":[3.720215334],"iteration":602,"passed_time":0.7596322603,"remaining_time":0.5001227319},
{"learn":[3.719436563],"iteration":603,"passed_time":0.7606894027,"remaining_time":0.4987301382},
{"learn":[3.715046574],"iteration":604,"passed_time":0.7618460976,"remaining_time":0.4974036505},
{"learn":[3.71443396],"iteration":605,"passed_time":0.7629793048,"remaining_time":0.4960624523},
{"learn":[3.712938941],"iteration":606,"passed_time":0.7640232881,"remaining_time":0.4946641717},
{"learn":[3.712814764],"iteration":607,"passed_time":0.7649397623,"remaining_time":0.4931848467},
{"learn":[3.71235348],"iteration":608,"passed_time":0.7659613441,"remaining_time":0.4917748531},
{"learn":[3.711223749],"iteration":609,"passed_time":0.7671783059,"remaining_time":0.490491048},
{"learn":[3.710755648],"iteration":610,"passed_time":0.768901348,"remaining_time":0.4895296635},
{"learn":[3.708668039],"iteration":611,"passed_time":0.7706463534,"remaining_time":0.4885797143},
{"learn":[3.705623591],"iteration":612,"passed_time":0.7719172504,"remaining_time":0.4873278563},
{"learn":[3.704045802],"iteration":613,"passed_time":0.7732776483,"remaining_time":0.4861322023},
{"learn":[3.699915209],"iteration":614,"passed_time":0.7745620667,"remaining_time":0.4848884483},
{"learn":[3.696182221],"iteration":615,"passed_time":0.775671711,"remaining_time":0.483535612},
{"learn":[3.694263278],"iteration":616,"passed_time":0.7768683228,"remaining_time":0.4822375489},
{"learn":[3.693810229],"iteration":617,"passed_time":0.7778169264,"remaining_time":0.4807865144},
{"learn":[3.690900932],"iteration":618,"passed_time":0.7788444641,"remaining_time":0.4793856879},
{"learn":[3.688020895],"iteration":619,"passed_time":0.779763944,"remaining_time":0.4779198367},
{"learn":[3.685491894],"iteration":620,"passed_time":0.7808789252,"remaining_time":0.4765750606},
{"learn":[3.684328128],"iteration":621,"passed_time":0.7818141065,"remaining_time":0.475121756},
{"learn":[3.680640153],"iteration":622,"passed_time":0.7830254443,"remaining_time":0.4738372271},
{"learn":[3.678932783],"iteration":623,"passed_time":0.7847403222,"remaining_time":0.472856348},
{"learn":[3.674167041],"iteration":624,"passed_time":0.785947309,"remaining_time":0.4715683854},
{"learn":[3.672200976],"iteration":625,"passed_time":0.7870783815,"remaining_time":0.4702353269},
{"learn":[3.670606604],"iteration":626,"passed_time":0.7883623188,"remaining_time":0.4689938515},
{"learn":[3.665506042],"iteration":627,"passed_time":0.789486012,"remaining_time":0.4676573192},
{"learn":[3.664214007],"iteration":628,"passed_time":0.7911440039,"remaining_time":0.4666366064},
{"learn":[3.66261643],"iteration":629,"passed_time":0.7923826962,"remaining_time":0.4653676152},
{"learn":[3.662118449],"iteration":630,"passed_time":0.7935124249,"remaining_time":0.4640349997},
{"learn":[3.660871366],"iteration":631,"passed_time":0.7945955578,"remaining_time":0.4626758944},
{"learn":[3.656695243],"iteration":632,"passed_time":0.79570729,"remaining_time":0.4613342424},
{"learn":[3.654497801],"iteration":633,"passed_time":0.7966698254,"remaining_time":0.4599071863},
{"learn":[3.654189134],"iteration":634,"passed_time":0.7978802654,"remaining_time":0.4586240896},
{"learn":[3.653957699],"iteration":635,"passed_time":0.7989842861,"remaining_time":0.4572803147},
{"learn":[3.651920725],"iteration":636,"passed_time":0.8006208426,"remaining_time":0.4562407627},
{"learn":[3.65106705],"iteration":637,"passed_time":0.8018210641,"remaining_time":0.4549517636},
{"learn":[3.650612844],"iteration":638,"passed_time":0.8030397579,"remaining_time":0.4536734783},
{"learn":[3.649884732],"iteration":639,"passed_time":0.8044469405,"remaining_time":0.452501404},
{"learn":[3.646276182],"iteration":640,"passed_time":0.8054161277,"remaining_time":0.4510832915},
{"learn":[3.645808194],"iteration":641,"passed_time":0.8063374608,"remaining_time":0.4496398924},
{"learn":[3.645042989],"iteration":642,"passed_time":0.8072969108,"remaining_time":0.4482192802},
{"learn":[3.639864499],"iteration":643,"passed_time":0.8083188693,"remaining_time":0.4468346545},
{"learn":[3.637318478],"iteration":644,"passed_time":0.809287249,"remaining_time":0.4454216642},
{"learn":[3.636344905],"iteration":645,"passed_time":0.8102398165,"remaining_time":0.4440013855},
{"learn":[3.634754643],"iteration":646,"passed_time":0.8111571573,"remaining_time":0.4425633331},
{"learn":[3.630724975],"iteration":647,"passed_time":0.8125015579,"remaining_time":0.441358871},
{"learn":[3.629408252],"iteration":648,"passed_time":0.8137898875,"remaining_time":0.4401236526},
{"learn":[3.62790646],"iteration":649,"passed_time":0.8153037594,"remaining_time":0.4390097166},
{"learn":[3.627388973],"iteration":650,"passed_time":0.8166133063,"remaining_time":0.4377850137},
{"learn":[3.625163557],"iteration":651,"passed_time":0.8181204793,"remaining_time":0.4366655319},
{"learn":[3.623701985],"iteration":652,"passed_time":0.8191613285,"remaining_time":0.4352970612},
{"learn":[3.622342639],"iteration":653,"passed_time":0.8202258053,"remaining_time":0.4339420927},
{"learn":[3.621130639],"iteration":654,"passed_time":0.821236787,"remaining_time":0.4325598344},
{"learn":[3.619125665],"iteration":655,"passed_time":0.822230632,"remaining_time":0.4311697217},
{"learn":[3.618878783],"iteration":656,"passed_time":0.823174655,"remaining_time":0.4297548047},
{"learn":[3.616207429],"iteration":657,"passed_time":0.8241707175,"remaining_time":0.4283683668},
{"learn":[3.61206486],"iteration":658,"passed_time":0.8251107829,"remaining_time":0.4269541381},
{"learn":[3.611955873],"iteration":659,"passed_time":0.826172504,"remaining_time":0.4256040172},
{"learn":[3.610713743],"iteration":660,"passed_time":0.8278533605,"remaining_time":0.4245722984},
{"learn":[3.610044025],"iteration":661,"passed_time":0.8291399464,"remaining_time":0.423337314},
{"learn":[3.607342669],"iteration":662,"passed_time":0.8308548699,"remaining_time":0.4223198962},
{"learn":[3.602510618],"iteration":663,"passed_time":0.8318518882,"remaining_time":0.4209371001},
{"learn":[3.600492392],"iteration":664,"passed_time":0.8328133235,"remaining_time":0.4195375389},
{"learn":[3.597171065],"iteration":665,"passed_time":0.8338781399,"remaining_time":0.4181911392},
{"learn":[3.594358798],"iteration":666,"passed_time":0.8349488234,"remaining_time":0.416848513},
{"learn":[3.593945251],"iteration":667,"passed_time":0.8358187037,"remaining_time":0.4154069006},
{"learn":[3.593607748],"iteration":668,"passed_time":0.8367038006,"remaining_time":0.4139745262},
{"learn":[3.592238714],"iteration":669,"passed_time":0.8377576486,"remaining_time":0.4126269016},
{"learn":[3.590144654],"iteration":670,"passed_time":0.8387355207,"remaining_time":0.4112429006},
{"learn":[3.587151536],"iteration":671,"passed_time":0.8397346437,"remaining_time":0.4098704809},
{"learn":[3.586070865],"iteration":672,"passed_time":0.840609694,"remaining_time":0.4084388855},
{"learn":[3.585102746],"iteration":673,"passed_time":0.8415713304,"remaining_time":0.4070508215},
{"learn":[3.584362847],"iteration":674,"passed_time":0.8426409026,"remaining_time":0.4057159901},
{"learn":[3.581407561],"iteration":675,"passed_time":0.8442168138,"remaining_time":0.4046246267},
{"learn":[3.57919422],"iteration":676,"passed_time":0.8457522574,"remaining_time":0.4035125246},
{"learn":[3.577632204],"iteration":677,"passed_time":0.8469044677,"remaining_time":0.4022171661},
{"learn":[3.573911195],"iteration":678,"passed_time":0.8481852337,"remaining_time":0.4009830044},
{"learn":[3.573408216],"iteration":679,"passed_time":0.8493732722,"remaining_time":0.3997050693},
{"learn":[3.571076482],"iteration":680,"passed_time":0.8506550564,"remaining_time":0.3984713113},
{"learn":[3.568177107],"iteration":681,"passed_time":0.8518015155,"remaining_time":0.3971743137},
{"learn":[3.564824621],"iteration":682,"passed_time":0.8528940903,"remaining_time":0.3958527476},
{"learn":[3.562475026],"iteration":683,"passed_time":0.8540422442,"remaining_time":0.394557528},
{"learn":[3.561226889],"iteration":684,"passed_time":0.8550570591,"remaining_time":0.3932014213},
{"learn":[3.559383467],"iteration":685,"passed_time":0.8564538015,"remaining_time":0.3920211278},
{"learn":[3.555209766],"iteration":686,"passed_time":0.8577817145,"remaining_time":0.3908088452},
{"learn":[3.55345383],"iteration":687,"passed_time":0.8593908625,"remaining_time":0.3897237632},
{"learn":[3.552300968],"iteration":688,"passed_time":0.8607531073,"remaining_time":0.3885257131},
{"learn":[3.551253986],"iteration":689,"passed_time":0.8619655853,"remaining_time":0.3872599006},
{"learn":[3.549807725],"iteration":690,"passed_time":0.8634655873,"remaining_time":0.3861228169},
{"learn":[3.547992926],"iteration":691,"passed_time":0.8649064263,"remaining_time":0.3849583516},
{"learn":[3.545438607],"iteration":692,"passed_time":0.8663809067,"remaining_time":0.3838079918},
{"learn":[3.543313763],"iteration":693,"passed_time":0.8676431871,"remaining_time":0.3825631344},
{"learn":[3.542962896],"iteration":694,"passed_time":0.8687417674,"remaining_time":0.3812463871},
{"learn":[3.539800465],"iteration":695,"passed_time":0.8698118042,"remaining_time":0.3799177996},
{"learn":[3.53953187],"iteration":696,"passed_time":0.8711119428,"remaining_time":0.3786899838},
{"learn":[3.536332425],"iteration":697,"passed_time":0.8723655347,"remaining_time":0.3774418216},
{"learn":[3.534993327],"iteration":698,"passed_time":0.8735857811,"remaining_time":0.3761792848},
{"learn":[3.531637011],"iteration":699,"passed_time":0.8748272252,"remaining_time":0.3749259536},
{"learn":[3.531040284],"iteration":700,"passed_time":0.8763470322,"remaining_time":0.3737913875},
{"learn":[3.529973872],"iteration":701,"passed_time":0.8776943441,"remaining_time":0.3725824994},
{"learn":[3.527325183],"iteration":702,"passed_time":0.8790745942,"remaining_time":0.371387133},
{"learn":[3.527200815],"iteration":703,"passed_time":0.8803304384,"remaining_time":0.3701389343},
{"learn":[3.523459911],"iteration":704,"passed_time":0.8822890991,"remaining_time":0.3691848003},
{"learn":[3.522729934],"iteration":705,"passed_time":0.8832912978,"remaining_time":0.3678295206},
{"learn":[3.522260582],"iteration":706,"passed_time":0.8843271697,"remaining_time":0.3664891948},
{"learn":[3.518641591],"iteration":707,"passed_time":0.8854938236,"remaining_time":0.3652036674},
{"learn":[3.516856405],"iteration":708,"passed_time":0.8865673646,"remaining_time":0.3638802582},
{"learn":[3.515083413],"iteration":709,"passed_time":0.8875988454,"remaining_time":0.3625403735},
{"learn":[3.514671214],"iteration":710,"passed_time":0.8887820625,"remaining_time":0.3612630325},
{"learn":[3.512617621],"iteration":711,"passed_time":0.8901021292,"remaining_time":0.3600413107},
{"learn":[3.510747971],"iteration":712,"passed_time":0.8915874877,"remaining_time":0.3588858471},
{"learn":[3.508149266],"iteration":713,"passed_time":0.8927116648,"remaining_time":0.3575847845},
{"learn":[3.504557165],"iteration":714,"passed_time":0.8939401765,"remaining_time":0.3563258046},
{"learn":[3.501367208],"iteration":715,"passed_time":0.8952278271,"remaining_time":0.3550903672},
{"learn":[3.497593362],"iteration":716,"passed_time":0.8961521467,"remaining_time":0.3537113773},
{"learn":[3.496291169],"iteration":717,"passed_time":0.8971937214,"remaining_time":0.3523797067},
{"learn":[3.49330374],"iteration":718,"passed_time":0.8982037536,"remaining_time":0.3510365157},
{"learn":[3.490044385],"iteration":719,"passed_time":0.8993147336,"remaining_time":0.3497335075},
{"learn":[3.488891789],"iteration":720,"passed_time":0.9001985913,"remaining_time":0.3483431442},
{"learn":[3.486869081],"iteration":721,"passed_time":0.9012282173,"remaining_time":0.3470103108},
{"learn":[3.486303638],"iteration":722,"passed_time":0.9022117369,"remaining_time":0.3456606516},
{"learn":[3.486035862],"iteration":723,"passed_time":0.9035245528,"remaining_time":0.3444375367},
{"learn":[3.482668951],"iteration":724,"passed_time":0.9049171757,"remaining_time":0.343244446},
{"learn":[3.47820549],"iteration":725,"passed_time":0.9064674701,"remaining_time":0.3421103124},
{"learn":[3.474392283],"iteration":726,"passed_time":0.9076332982,"remaining_time":0.3408306608},
{"learn":[3.472268163],"iteration":727,"passed_time":0.908666252,"remaining_time":0.3395016766},
{"learn":[3.471209164],"iteration":728,"passed_time":0.9095826073,"remaining_time":0.3381301599},
{"learn":[3.470049971],"iteration":729,"passed_time":0.910583602,"remaining_time":0.3367911953},
{"learn":[3.469078654],"iteration":730,"passed_time":0.9115820404,"remaining_time":0.3354522146},
{"learn":[3.468643292],"iteration":731,"passed_time":0.912682753,"remaining_time":0.334151609},
{"learn":[3.468134848],"iteration":732,"passed_time":0.9135959711,"remaining_time":0.3327832528},
{"learn":[3.467820182],"iteration":733,"passed_time":0.9146937971,"remaining_time":0.3314830382},
{"learn":[3.465776156],"iteration":734,"passed_time":0.9156666471,"remaining_time":0.3301383149},
{"learn":[3.463037608],"iteration":735,"passed_time":0.9165802742,"remaining_time":0.3287733592},
{"learn":[3.45965637],"iteration":736,"passed_time":0.9177047873,"remaining_time":0.3274848834},
{"learn":[3.457275091],"iteration":737,"passed_time":0.9192406332,"remaining_time":0.3263428806},
{"learn":[3.455522955],"iteration":738,"passed_time":0.9207077184,"remaining_time":0.3251755271},
{"learn":[3.451270508],"iteration":739,"passed_time":0.9219099583,"remaining_time":0.3239143097},
{"learn":[3.450978947],"iteration":740,"passed_time":0.9228492391,"remaining_time":0.32256134},
{"learn":[3.450608492],"iteration":741,"passed_time":0.9239008119,"remaining_time":0.3212485303},
{"learn":[3.448122004],"iteration":742,"passed_time":0.9248681055,"remaining_time":0.319907272},
{"learn":[3.445646714],"iteration":743,"passed_time":0.9258770096,"remaining_time":0.3185813366},
{"learn":[3.44411263],"iteration":744,"passed_time":0.9269332967,"remaining_time":0.3172724707},
{"learn":[3.443264164],"iteration":745,"passed_time":0.9279504738,"remaining_time":0.3159509656},
{"learn":[3.439521363],"iteration":746,"passed_time":0.9290217476,"remaining_time":0.3146485972},
{"learn":[3.436809225],"iteration":747,"passed_time":0.9299931095,"remaining_time":0.3133131866},
{"learn":[3.435509465],"iteration":748,"passed_time":0.9309696554,"remaining_time":0.3119804853},
{"learn":[3.434450277],"iteration":749,"passed_time":0.9324498858,"remaining_time":0.3108166286},
{"learn":[3.431786753],"iteration":750,"passed_time":0.9339831623,"remaining_time":0.3096695172},
{"learn":[3.430150302],"iteration":751,"passed_time":0.9357618131,"remaining_time":0.3086023001},
{"learn":[3.42696281],"iteration":752,"passed_time":0.9370631847,"remaining_time":0.3073766356},
{"learn":[3.426870334],"iteration":753,"passed_time":0.9380932338,"remaining_time":0.3060622487},
{"learn":[3.425200309],"iteration":754,"passed_time":0.9391743923,"remaining_time":0.3047652001},
{"learn":[3.423383783],"iteration":755,"passed_time":0.9401370824,"remaining_time":0.3034304869},
{"learn":[3.422752979],"iteration":756,"passed_time":0.9412009242,"remaining_time":0.3021292267},
{"learn":[3.420845924],"iteration":757,"passed_time":0.9421248904,"remaining_time":0.300783936},
{"learn":[3.418917862],"iteration":758,"passed_time":0.9431514371,"remaining_time":0.2994723272},
{"learn":[3.417095735],"iteration":759,"passed_time":0.9440851955,"remaining_time":0.298132167},
{"learn":[3.414391848],"iteration":760,"passed_time":0.9450949226,"remaining_time":0.2968169337},
{"learn":[3.41426711],"iteration":761,"passed_time":0.9461539183,"remaining_time":0.2955178905},
{"learn":[3.411976013],"iteration":762,"passed_time":0.9470789626,"remaining_time":0.2941778691},
{"learn":[3.408614844],"iteration":763,"passed_time":0.948029293,"remaining_time":0.292846745},
{"learn":[3.407906721],"iteration":764,"passed_time":0.9494466154,"remaining_time":0.2916600714},
{"learn":[3.407494015],"iteration":765,"passed_time":0.9515121397,"remaining_time":0.2906708103},
{"learn":[3.406287128],"iteration":766,"passed_time":0.9527010477,"remaining_time":0.2894124434},
{"learn":[3.404600442],"iteration":767,"passed_time":0.9538836533,"remaining_time":0.2881523536},
{"learn":[3.404012662],"iteration":768,"passed_time":0.9550511431,"remaining_time":0.2868879246},
{"learn":[3.400398762],"iteration":769,"passed_time":0.9560955031,"remaining_time":0.2855869685},
{"learn":[3.399737714],"iteration":770,"passed_time":0.9572088778,"remaining_time":0.2843071764},
{"learn":[3.399185251],"iteration":771,"passed_time":0.9583277941,"remaining_time":0.2830294521},
{"learn":[3.397245411],"iteration":772,"passed_time":0.9593296317,"remaining_time":0.2817177573},
{"learn":[3.396229831],"iteration":773,"passed_time":0.9605668632,"remaining_time":0.2804755957},
{"learn":[3.394002836],"iteration":774,"passed_time":0.9616085022,"remaining_time":0.2791766619},
{"learn":[3.389617243],"iteration":775,"passed_time":0.9625613541,"remaining_time":0.277852762},
{"learn":[3.385426488],"iteration":776,"passed_time":0.963509349,"remaining_time":0.2765284232},
{"learn":[3.385072258],"iteration":777,"passed_time":0.9644657425,"remaining_time":0.2752074484},
{"learn":[3.383842366],"iteration":778,"passed_time":0.9657714675,"remaining_time":0.2739865139},
{"learn":[3.380110746],"iteration":779,"passed_time":0.9674259785,"remaining_time":0.2728637375},
{"learn":[3.378595218],"iteration":780,"passed_time":0.968464695,"remaining_time":0.2715669247},
{"learn":[3.377371219],"iteration":781,"passed_time":0.969534815,"remaining_time":0.2702795264},
{"learn":[3.375814782],"iteration":782,"passed_time":0.9709372331,"remaining_time":0.269084776},
{"learn":[3.374195887],"iteration":783,"passed_time":0.9722711947,"remaining_time":0.2678706353},
{"learn":[3.373704309],"iteration":784,"passed_time":0.9735313084,"remaining_time":0.2666359634},
{"learn":[3.372971757],"iteration":785,"passed_time":0.9748073106,"remaining_time":0.2654055528},
{"learn":[3.371565136],"iteration":786,"passed_time":0.9758961294,"remaining_time":0.2641243654},
{"learn":[3.3700309],"iteration":787,"passed_time":0.9768753212,"remaining_time":0.2628141727},
{"learn":[3.368186663],"iteration":788,"passed_time":0.9777941585,"remaining_time":0.2614886786},
{"learn":[3.366710398],"iteration":789,"passed_time":0.9788430703,"remaining_time":0.2601987908},
{"learn":[3.364598042],"iteration":790,"passed_time":0.9801571487,"remaining_time":0.2589795753},
{"learn":[3.36348442],"iteration":791,"passed_time":0.9817439496,"remaining_time":0.2578317443},
{"learn":[3.362001759],"iteration":792,"passed_time":0.9828377921,"remaining_time":0.2565541273},
{"learn":[3.361580401],"iteration":793,"passed_time":0.9837534348,"remaining_time":0.25523074},
{"learn":[3.359543675],"iteration":794,"passed_time":0.9847790433,"remaining_time":0.2539367344},
{"learn":[3.35766119],"iteration":795,"passed_time":0.9856871697,"remaining_time":0.2526132947},
{"learn":[3.354592969],"iteration":796,"passed_time":0.9867524124,"remaining_time":0.2513309156},
{"learn":[3.350985986],"iteration":797,"passed_time":0.9877045752,"remaining_time":0.2500204564},
{"learn":[3.349589624],"iteration":798,"passed_time":0.9888517602,"remaining_time":0.2487599547},
{"learn":[3.349110856],"iteration":799,"passed_time":0.9901325842,"remaining_time":0.247533146},
{"learn":[3.345315441],"iteration":800,"passed_time":0.9912526006,"remaining_time":0.2462662516},
{"learn":[3.34397474],"iteration":801,"passed_time":0.9923091396,"remaining_time":0.2449840519},
{"learn":[3.343800902],"iteration":802,"passed_time":0.9933704776,"remaining_time":0.2437035916},
{"learn":[3.342329465],"iteration":803,"passed_time":0.9946754755,"remaining_time":0.2424830761},
{"learn":[3.34220347],"iteration":804,"passed_time":0.9962624324,"remaining_time":0.2413306513},
{"learn":[3.341279219],"iteration":805,"passed_time":0.9976251326,"remaining_time":0.2401231709},
{"learn":[3.337329521],"iteration":806,"passed_time":0.998965794,"remaining_time":0.238910035},
{"learn":[3.336708453],"iteration":807,"passed_time":1.000230358,"remaining_time":0.237678501},
{"learn":[3.333252703],"iteration":808,"passed_time":1.001427253,"remaining_time":0.2364309088},
{"learn":[3.332186769],"iteration":809,"passed_time":1.002944775,"remaining_time":0.235258651},
{"learn":[3.330594851],"iteration":810,"passed_time":1.004679745,"remaining_time":0.2341362168},
{"learn":[3.327867442],"iteration":811,"passed_time":1.005869859,"remaining_time":0.2328861249},
{"learn":[3.327563111],"iteration":812,"passed_time":1.006906795,"remaining_time":0.231600948},
{"learn":[3.326308994],"iteration":813,"passed_time":1.007982139,"remaining_time":0.230325157},
{"learn":[3.326249879],"iteration":814,"passed_time":1.009205633,"remaining_time":0.2290834872},
{"learn":[3.322336238],"iteration":815,"passed_time":1.010732684,"remaining_time":0.2279103111},
{"learn":[3.320491154],"iteration":816,"passed_time":1.012531037,"remaining_time":0.2267970378},
{"learn":[3.320434271],"iteration":817,"passed_time":1.013629479,"remaining_time":0.2255263634},
{"learn":[3.319609638],"iteration":818,"passed_time":1.014625072,"remaining_time":0.2242333798},
{"learn":[3.316182682],"iteration":819,"passed_time":1.015653205,"remaining_time":0.2229482644},
{"learn":[3.313126612],"iteration":820,"passed_time":1.016676948,"remaining_time":0.2216628181},
{"learn":[3.311222803],"iteration":821,"passed_time":1.017633368,"remaining_time":0.22036343},
{"learn":[3.309627335],"iteration":822,"passed_time":1.018644877,"remaining_time":0.2190767233},
{"learn":[3.307974895],"iteration":823,"passed_time":1.019670023,"remaining_time":0.2177935972},
{"learn":[3.307321505],"iteration":824,"passed_time":1.020602275,"remaining_time":0.2164913916},
{"learn":[3.306759087],"iteration":825,"passed_time":1.021679758,"remaining_time":0.2152206755},
{"learn":[3.30484037],"iteration":826,"passed_time":1.022603004,"remaining_time":0.2139181616},
{"learn":[3.30201994],"iteration":827,"passed_time":1.023896118,"remaining_time":0.2126933964},
{"learn":[3.299302297],"iteration":828,"passed_time":1.02524056,"remaining_time":0.2114790541},
{"learn":[3.298132671],"iteration":829,"passed_time":1.027464552,"remaining_time":0.2104445468},
{"learn":[3.296976183],"iteration":830,"passed_time":1.028604983,"remaining_time":0.2091868136},
{"learn":[3.293144745],"iteration":831,"passed_time":1.029700096,"remaining_time":0.2079202116},
{"learn":[3.290284404],"iteration":832,"passed_time":1.030763272,"remaining_time":0.2066476189},
{"learn":[3.288285745],"iteration":833,"passed_time":1.031720679,"remaining_time":0.2053544756},
{"learn":[3.286662667],"iteration":834,"passed_time":1.032750341,"remaining_time":0.2040764146},
{"learn":[3.285692682],"iteration":835,"passed_time":1.033714166,"remaining_time":0.2027860326},
{"learn":[3.284565611],"iteration":836,"passed_time":1.034806065,"remaining_time":0.2015213724},
{"learn":[3.283897383],"iteration":837,"passed_time":1.035715844,"remaining_time":0.2002219173},
{"learn":[3.280712855],"iteration":838,"passed_time":1.036786219,"remaining_time":0.198954209},
{"learn":[3.280468341],"iteration":839,"passed_time":1.037823064,"remaining_time":0.1976805837},
{"learn":[3.277814895],"iteration":840,"passed_time":1.038992764,"remaining_time":0.196432639},
{"learn":[3.276316385],"iteration":841,"passed_time":1.040324471,"remaining_time":0.1952152808},
{"learn":[3.27557063],"iteration":842,"passed_time":1.042011955,"remaining_time":0.194063911},
{"learn":[3.27499628],"iteration":843,"passed_time":1.043033947,"remaining_time":0.1927882651},
{"learn":[3.273569958],"iteration":844,"passed_time":1.044187452,"remaining_time":0.1915373434},
{"learn":[3.269665595],"iteration":845,"passed_time":1.045126651,"remaining_time":0.190247641},
{"learn":[3.267984685],"iteration":846,"passed_time":1.046112227,"remaining_time":0.1889671437},
{"learn":[3.267702508],"iteration":847,"passed_time":1.047116724,"remaining_time":0.1876907336},
{"learn":[3.266671924],"iteration":848,"passed_time":1.04809303,"remaining_time":0.18640995},
{"learn":[3.265359825],"iteration":849,"passed_time":1.049060226,"remaining_time":0.1851282752},
{"learn":[3.2618983],"iteration":850,"passed_time":1.050060125,"remaining_time":0.1838530654},
{"learn":[3.260456253],"iteration":851,"passed_time":1.051025817,"remaining_time":0.1825725598},
{"learn":[3.258389147],"iteration":852,"passed_time":1.052099781,"remaining_time":0.1813114511},
{"learn":[3.258108469],"iteration":853,"passed_time":1.053078355,"remaining_time":0.1800344729},
{"learn":[3.256424936],"iteration":854,"passed_time":1.054233865,"remaining_time":0.1787881993},
{"learn":[3.254817983],"iteration":855,"passed_time":1.055916545,"remaining_time":0.1776308206},
{"learn":[3.253898449],"iteration":856,"passed_time":1.05760343,"remaining_time":0.1764729177},
{"learn":[3.253023652],"iteration":857,"passed_time":1.058756461,"remaining_time":0.1752254282},
{"learn":[3.252845542],"iteration":858,"passed_time":1.059879734,"remaining_time":0.1739732741},
{"learn":[3.252316026],"iteration":859,"passed_time":1.061007852,"remaining_time":0.1727222084},
{"learn":[3.24975301],"iteration":860,"passed_time":1.062215427,"remaining_time":0.171484256},
{"learn":[3.249151075],"iteration":861,"passed_time":1.06353789,"remaining_time":0.1702647667},
{"learn":[3.246257135],"iteration":862,"passed_time":1.06501148,"remaining_time":0.1690690299},
{"learn":[3.243826471],"iteration":863,"passed_time":1.066170927,"remaining_time":0.1678232015},
{"learn":[3.243190653],"iteration":864,"passed_time":1.067137156,"remaining_time":0.1665474174},
{"learn":[3.24008797],"iteration":865,"passed_time":1.068191528,"remaining_time":0.165285987},
{"learn":[3.240036811],"iteration":866,"passed_time":1.069377252,"remaining_time":0.164045184},
{"learn":[3.238676314],"iteration":867,"passed_time":1.070850252,"remaining_time":0.162848195},
{"learn":[3.237848782],"iteration":868,"passed_time":1.072432432,"remaining_time":0.1616670294},
{"learn":[3.236405498],"iteration":869,"passed_time":1.073630135,"remaining_time":0.1604274914},
{"learn":[3.233378068],"iteration":870,"passed_time":1.074805228,"remaining_time":0.1591847009},
{"learn":[3.233169169],"iteration":871,"passed_time":1.075856709,"remaining_time":0.1579239206},
{"learn":[3.232434885],"iteration":872,"passed_time":1.077031235,"remaining_time":0.1566815198},
{"learn":[3.229978115],"iteration":873,"passed_time":1.078110471,"remaining_time":0.155425537},
{"learn":[3.229648848],"iteration":874,"passed_time":1.079360185,"remaining_time":0.1541943121},
{"learn":[3.227208761],"iteration":875,"passed_time":1.080539976,"remaining_time":0.1529531473},
{"learn":[3.226258869],"iteration":876,"passed_time":1.081584488,"remaining_time":0.1516931494},
{"learn":[3.225331995],"iteration":877,"passed_time":1.082612946,"remaining_time":0.1504314116},
{"learn":[3.221968268],"iteration":878,"passed_time":1.083562171,"remaining_time":0.1491592978},
{"learn":[3.221166317],"iteration":879,"passed_time":1.08468138,"remaining_time":0.1479110973},
{"learn":[3.220047503],"iteration":880,"passed_time":1.085999903,"remaining_time":0.1466901118},
{"learn":[3.21982781],"iteration":881,"passed_time":1.087609457,"remaining_time":0.1455078412},
{"learn":[3.216693405],"iteration":882,"passed_time":1.088921121,"remaining_time":0.1442851315},
{"learn":[3.214798761],"iteration":883,"passed_time":1.090243245,"remaining_time":0.1430635933},
{"learn":[3.214395085],"iteration":884,"passed_time":1.091390028,"remaining_time":0.1418190431},
{"learn":[3.213470696],"iteration":885,"passed_time":1.092717501,"remaining_time":0.1405979628},
{"learn":[3.211595017],"iteration":886,"passed_time":1.094302984,"remaining_time":0.139409512},
{"learn":[3.210965255],"iteration":887,"passed_time":1.095570056,"remaining_time":0.138180007},
{"learn":[3.209413583],"iteration":888,"passed_time":1.096795605,"remaining_time":0.136945233},
{"learn":[3.208331683],"iteration":889,"passed_time":1.097805057,"remaining_time":0.1356837711},
{"learn":[3.207110711],"iteration":890,"passed_time":1.098854811,"remaining_time":0.1344278052},
{"learn":[3.204519413],"iteration":891,"passed_time":1.100063663,"remaining_time":0.1331915646},
{"learn":[3.201421296],"iteration":892,"passed_time":1.101207116,"remaining_time":0.1319475492},
{"learn":[3.200691259],"iteration":893,"passed_time":1.102832152,"remaining_time":0.1307608591},
{"learn":[3.200485067],"iteration":894,"passed_time":1.104182568,"remaining_time":0.1295409717},
{"learn":[3.197467568],"iteration":895,"passed_time":1.10520327,"remaining_time":0.1282825224},
{"learn":[3.195838544],"iteration":896,"passed_time":1.106244247,"remaining_time":0.1270269314},
{"learn":[3.195671746],"iteration":897,"passed_time":1.107260788,"remaining_time":0.1257690427},
{"learn":[3.194213094],"iteration":898,"passed_time":1.108405511,"remaining_time":0.1245260919},
{"learn":[3.192884691],"iteration":899,"passed_time":1.109362519,"remaining_time":0.1232625021},
{"learn":[3.188364239],"iteration":900,"passed_time":1.110351799,"remaining_time":0.1220031388},
{"learn":[3.185219478],"iteration":901,"passed_time":1.111329983,"remaining_time":0.1207431689},
{"learn":[3.184120387],"iteration":902,"passed_time":1.112333914,"remaining_time":0.1194865887},
{"learn":[3.183725321],"iteration":903,"passed_time":1.113317581,"remaining_time":0.1182284157},
{"learn":[3.181264554],"iteration":904,"passed_time":1.114303027,"remaining_time":0.116971036},
{"learn":[3.180741589],"iteration":905,"passed_time":1.115709306,"remaining_time":0.1157579192},
{"learn":[3.179782639],"iteration":906,"passed_time":1.117325752,"remaining_time":0.114565926},
{"learn":[3.176377564],"iteration":907,"passed_time":1.11834009,"remaining_time":0.1133119915},
{"learn":[3.174078182],"iteration":908,"passed_time":1.11932894,"remaining_time":0.1120560325},
{"learn":[3.171242379],"iteration":909,"passed_time":1.120312756,"remaining_time":0.1108001627},
{"learn":[3.170421012],"iteration":910,"passed_time":1.121321944,"remaining_time":0.1095473688},
{"learn":[3.170087224],"iteration":911,"passed_time":1.122235982,"remaining_time":0.1082859281},
{"learn":[3.167303059],"iteration":912,"passed_time":1.123335052,"remaining_time":0.1070428801},
{"learn":[3.16705966],"iteration":913,"passed_time":1.124243872,"remaining_time":0.1057822462},
{"learn":[3.165667683],"iteration":914,"passed_time":1.125203731,"remaining_time":0.1045271225},
{"learn":[3.164689733],"iteration":915,"passed_time":1.126330164,"remaining_time":0.103287919},
{"learn":[3.163311455],"iteration":916,"passed_time":1.12752372,"remaining_time":0.1020550368},
{"learn":[3.159425016],"iteration":917,"passed_time":1.12846381,"remaining_time":0.1007995996},
{"learn":[3.159327058],"iteration":918,"passed_time":1.1295376,"remaining_time":0.09955663291},
{"learn":[3.15819426],"iteration":919,"passed_time":1.130727121,"remaining_time":0.09832409752},
{"learn":[3.157086603],"iteration":920,"passed_time":1.132442014,"remaining_time":0.09713672},
{"learn":[3.153354154],"iteration":921,"passed_time":1.133855599,"remaining_time":0.09592270791},
{"learn":[3.153261317],"iteration":922,"passed_time":1.134904263,"remaining_time":0.09467782042},
{"learn":[3.153168454],"iteration":923,"passed_time":1.135838546,"remaining_time":0.09342394964},
{"learn":[3.152080399],"iteration":924,"passed_time":1.136798909,"remaining_time":0.09217288452},
{"learn":[3.151635144],"iteration":925,"passed_time":1.137718413,"remaining_time":0.09091918206},
{"learn":[3.147762655],"iteration":926,"passed_time":1.138806941,"remaining_time":0.08967951103},
{"learn":[3.147172317],"iteration":927,"passed_time":1.13981075,"remaining_time":0.08843359269},
{"learn":[3.146254125],"iteration":928,"passed_time":1.140794203,"remaining_time":0.08718663982},
{"learn":[3.144869828],"iteration":929,"passed_time":1.141779697,"remaining_time":0.08594040734},
{"learn":[3.143466218],"iteration":930,"passed_time":1.142794993,"remaining_time":0.08469694366},
{"learn":[3.141919643],"iteration":931,"passed_time":1.143809252,"remaining_time":0.08345389392},
{"learn":[3.141054135],"iteration":932,"passed_time":1.144850398,"remaining_time":0.08221326542},
{"learn":[3.139390417],"iteration":933,"passed_time":1.146336531,"remaining_time":0.08100450864},
{"learn":[3.139025283],"iteration":934,"passed_time":1.14800957,"remaining_time":0.0798081519},
{"learn":[3.137824183],"iteration":935,"passed_time":1.149230787,"remaining_time":0.07857988287},
{"learn":[3.135620453],"iteration":936,"passed_time":1.150400687,"remaining_time":0.0773481785},
{"learn":[3.13443178],"iteration":937,"passed_time":1.151656528,"remaining_time":0.07612228649},
{"learn":[3.132765713],"iteration":938,"passed_time":1.152732781,"remaining_time":0.07488466416},
{"learn":[3.131434124],"iteration":939,"passed_time":1.153841464,"remaining_time":0.07364945517},
{"learn":[3.128384262],"iteration":940,"passed_time":1.155041939,"remaining_time":0.07242027032},
{"learn":[3.128120455],"iteration":941,"passed_time":1.155927801,"remaining_time":0.07117177543},
{"learn":[3.126314615],"iteration":942,"passed_time":1.157064275,"remaining_time":0.06993919794},
{"learn":[3.125409666],"iteration":943,"passed_time":1.158099104,"remaining_time":0.06870079433},
{"learn":[3.123072589],"iteration":944,"passed_time":1.159298765,"remaining_time":0.06747241488},
{"learn":[3.122921099],"iteration":945,"passed_time":1.161066661,"remaining_time":0.06627653245},
{"learn":[3.122182662],"iteration":946,"passed_time":1.162946164,"remaining_time":0.06508568815},
{"learn":[3.120040951],"iteration":947,"passed_time":1.164320145,"remaining_time":0.06386566197},
{"learn":[3.118767799],"iteration":948,"passed_time":1.165443859,"remaining_time":0.06263186175},
{"learn":[3.118203218],"iteration":949,"passed_time":1.166468086,"remaining_time":0.06139305714},
{"learn":[3.116343362],"iteration":950,"passed_time":1.167421167,"remaining_time":0.06015103803},
{"learn":[3.11480829],"iteration":951,"passed_time":1.168393545,"remaining_time":0.05891059889},
{"learn":[3.112607903],"iteration":952,"passed_time":1.169431588,"remaining_time":0.05767396078},
{"learn":[3.111661241],"iteration":953,"passed_time":1.170370382,"remaining_time":0.05643295344},
{"learn":[3.110249676],"iteration":954,"passed_time":1.171415067,"remaining_time":0.05519756862},
{"learn":[3.107333579],"iteration":955,"passed_time":1.172415319,"remaining_time":0.05396053769},
{"learn":[3.107149851],"iteration":956,"passed_time":1.17383035,"remaining_time":0.0527426385},
{"learn":[3.106867336],"iteration":957,"passed_time":1.175140749,"remaining_time":0.05151974058},
{"learn":[3.10364681],"iteration":958,"passed_time":1.17651926,"remaining_time":0.05029957211},
{"learn":[3.102703811],"iteration":959,"passed_time":1.178253548,"remaining_time":0.04909389785},
{"learn":[3.101469264],"iteration":960,"passed_time":1.179123615,"remaining_time":0.04785205099},
{"learn":[3.09863569],"iteration":961,"passed_time":1.180170247,"remaining_time":0.04661795156},
{"learn":[3.09645939],"iteration":962,"passed_time":1.181202302,"remaining_time":0.04538368137},
{"learn":[3.096240186],"iteration":963,"passed_time":1.182169209,"remaining_time":0.04414739784},
{"learn":[3.094838828],"iteration":964,"passed_time":1.183170337,"remaining_time":0.04291291378},
{"learn":[3.094176802],"iteration":965,"passed_time":1.184224961,"remaining_time":0.04168079571},
{"learn":[3.093182279],"iteration":966,"passed_time":1.185126103,"remaining_time":0.04044380704},
{"learn":[3.090150687],"iteration":967,"passed_time":1.186084234,"remaining_time":0.03920939615},
{"learn":[3.088612829],"iteration":968,"passed_time":1.187076491,"remaining_time":0.03797664728},
{"learn":[3.087153684],"iteration":969,"passed_time":1.188129406,"remaining_time":0.0367462703},
{"learn":[3.085866843],"iteration":970,"passed_time":1.189067978,"remaining_time":0.03551284382},
{"learn":[3.082669094],"iteration":971,"passed_time":1.189981377,"remaining_time":0.03427929892},
{"learn":[3.081047548],"iteration":972,"passed_time":1.191169839,"remaining_time":0.03305404486},
{"learn":[3.079684322],"iteration":973,"passed_time":1.192389912,"remaining_time":0.03182971018},
{"learn":[3.07613431],"iteration":974,"passed_time":1.193418522,"remaining_time":0.03060047493},
{"learn":[3.074005935],"iteration":975,"passed_time":1.194472863,"remaining_time":0.02937228351},
{"learn":[3.072988853],"iteration":976,"passed_time":1.195782366,"remaining_time":0.02815045488},
{"learn":[3.072344268],"iteration":977,"passed_time":1.196985943,"remaining_time":0.02692606415},
{"learn":[3.070654438],"iteration":978,"passed_time":1.198114003,"remaining_time":0.02570009607},
{"learn":[3.069724506],"iteration":979,"passed_time":1.199738151,"remaining_time":0.02448445205},
{"learn":[3.067763166],"iteration":980,"passed_time":1.200796271,"remaining_time":0.02325701238},
{"learn":[3.066737893],"iteration":981,"passed_time":1.201889064,"remaining_time":0.0220305531},
{"learn":[3.065248174],"iteration":982,"passed_time":1.202937736,"remaining_time":0.02080360276},
{"learn":[3.063186837],"iteration":983,"passed_time":1.20396898,"remaining_time":0.01957673139},
{"learn":[3.062880371],"iteration":984,"passed_time":1.205003136,"remaining_time":0.01835030157},
{"learn":[3.061288645],"iteration":985,"passed_time":1.206237699,"remaining_time":0.01712710729},
{"learn":[3.059970575],"iteration":986,"passed_time":1.207827064,"remaining_time":0.01590856315},
{"learn":[3.059576341],"iteration":987,"passed_time":1.209758769,"remaining_time":0.01469342635},
{"learn":[3.058175919],"iteration":988,"passed_time":1.210921811,"remaining_time":0.01346829113},
{"learn":[3.056830702],"iteration":989,"passed_time":1.211965451,"remaining_time":0.01224207526},
{"learn":[3.056336579],"iteration":990,"passed_time":1.212879708,"remaining_time":0.01101505285},
{"learn":[3.055810414],"iteration":991,"passed_time":1.213825605,"remaining_time":0.00978891617},
{"learn":[3.055476518],"iteration":992,"passed_time":1.214752685,"remaining_time":0.008563211274},
{"learn":[3.053331734],"iteration":993,"passed_time":1.215809831,"remaining_time":0.007338892343},
{"learn":[3.050890374],"iteration":994,"passed_time":1.216864358,"remaining_time":0.00611489627},
{"learn":[3.04972623],"iteration":995,"passed_time":1.217879209,"remaining_time":0.004891081162},
{"learn":[3.047217327],"iteration":996,"passed_time":1.218920906,"remaining_time":0.003667766015},
{"learn":[3.047155483],"iteration":997,"passed_time":1.219925717,"remaining_time":0.002444740917},
{"learn":[3.04430671],"iteration":998,"passed_time":1.221914286,"remaining_time":0.001223137423},
{"learn":[3.042664195],"iteration":999,"passed_time":1.223796636,"remaining_time":0}
]}